Workbook
Name AE_Ben_All: '[1]B-IV - All Else'!$Z$42:$AS$42
Name AE_CountCost: '[1]DB - Departments'!$F$11:$H$20
Name AE_DeptList: '[1]DB - Departments'!$B$47:$B$56
Name AE_DeptList_Code: '[1]DB - Departments'!$B$47:$C$56
Name AppGrowth: '[1]DB - Cert Growth'!$M$47:$AF$47
Name Assm_HWSWCost: [1]Assumptions!$B$20
Name Assm_ImpCont: [1]Assumptions!$B$22
Name Assm_PayInc: [1]Assumptions!$B$18
Name Assm_RetBon: '[1]C-V - Other Emp Costs'!$F$47
Name Assm_SevRate: '[1]C-V - Other Emp Costs'!$G$25
Name BA_Hourly: [2]Dashboard!$C$20
Name Ben_Input: '[1]Benefit Input'!$A$10:$Y$76
Name Ben_Prob: '[1]Benefit Probabilities'!$A$10:$CL$76
Name BT_Ben_Intfc: '[1]B-II - Bus Tech'!$AO$69:$CB$69
Name BT_Ben_ModSys: '[1]B-II - Bus Tech'!$AO$73:$CB$73
Name BT_Ben_PASSuppt: '[1]B-II - Bus Tech'!$AO$67:$CB$67
Name BT_Ben_SpnCntl: '[1]B-II - Bus Tech'!$AO$75:$CB$75
Name BT_Ben_TechRat: '[1]B-II - Bus Tech'!$AO$71:$CB$71
Name BT_DeptList: '[1]DB - Departments'!$B$11:$B$21
Name BT_DeptList_Code: '[1]DB - Departments'!$B$11:$C$21
Name BUS_COST_HOUR: [3]Assumptions!$E$9
Name CertGrowth: '[1]DB - Cert Growth'!$L$10:$BT$21
Name CertGrowth_Prod: '[1]DB - Cert Growth'!$L$10:$L$21
Name CertGrowth_YrSys: '[1]DB - Cert Growth'!$L$10:$BT$10
Name ClaimsGrowth: '[1]DB - Cert Growth'!$M$77:$AF$77
Name CO_Ben_Auto: '[1]B-III - Core Ops'!$AR$131:$BK$131
Name CO_Ben_Claims: '[1]B-III - Core Ops'!$AR$135:$BK$135
Name CO_Ben_CSInt: '[1]B-III - Core Ops'!$AR$133:$BK$133
Name CO_Ben_OneSys: '[1]B-III - Core Ops'!$AR$129:$BK$129
Name CO_Ben_OutAuto: '[1]B-III - Core Ops'!$AR$137:$BK$137
Name CO_Ben_PmtMeth: '[1]B-III - Core Ops'!$AR$139:$BK$139
Name CO_Ben_SelfSvc: '[1]B-III - Core Ops'!$AR$141:$BK$141
Name CO_Ben_SpnCntrl: '[1]B-III - Core Ops'!$AR$143:$BK$143
Name CO_DeptList: '[1]DB - Departments'!$B$23:$B$45
Name CO_DeptList_Code: '[1]DB - Departments'!$B$23:$C$45
Name CONTINGENCY: [3]Assumptions!$E$84
Name Cost_Input: '[1]Cost Input'!$A$11:$Y$66
Name Cost_Prob: '[1]Cost Probabilities'!$A$10:$CL$60
Name CSC_Gap_Imp: '[1]V - CSC'!$E$96:$X$96
Name CSC_Gap_Recur: '[1]V - CSC'!$E$89:$X$89
Name CSC_OneTime: '[1]V - CSC'!$E$52:$X$52
Name CSC_Recurring: '[1]V - CSC'!$E$13:$X$13
Name Dash_Best: OFFSET('[1]Dashboard Input'!$C$9,0,0,,COUNT('[1]Dashboard Input'!$C$9:$V$9))
Name Dash_Probable: OFFSET('[1]Dashboard Input'!$C$8,0,0,,COUNT('[1]Dashboard Input'!$C$8:$V$8))
Name Dash_Submitted: OFFSET('[1]Dashboard Input'!$C$6,0,0,,COUNT('[1]Dashboard Input'!$C$6:$V$6))
Name Dash_Worst: OFFSET('[1]Dashboard Input'!$C$7,0,0,,COUNT('[1]Dashboard Input'!$C$7:$V$7))
Name DISCOUNT: [3]Assumptions!$E$7
Name Discount_Rate: [4]Dashboard!$C$10
Name DiscRate: '[5]Benefit Summary'!$D$5
Name FIN_Consult: [2]Dashboard!$C$28
Name FIN_PMO: [2]Dashboard!$C$29
Name FIN_Training: [2]Dashboard!$C$27
Name FTE_AE_Total: '[1]B-IV - All Else'!$M$42
Name FTE_BT_Efcy: '[1]B-II - Bus Tech'!$AF$67
Name FTE_BT_Suppt: '[1]B-II - Bus Tech'!$I$67
Name FTE_CO_Efcy: '[1]B-III - Core Ops'!$AF$127
Name FTE_CO_SpanCntl: '[1]B-III - Core Ops'!$AH$127
Name Group_GR: [2]Dashboard!$C$13
Name Hours_Day: [2]Dashboard!$C$30
Name Hours_Yr: [2]Dashboard!$C$25

Sheet Overview
I1: Status | N1: Priority
A2: Tab | B2: E2E Process | C2: Level 1 | D2: Level 2 | E2: Level 3 | F2: Sheet | G2: SRE - Direct | H2: Requirements | I2: Open | J2: FIT | K2: FIT Customizing | L2: GAP | M2: GAP Customizing | N2: High | O2: Medium | P2: Low | Q2: Progress | R2: Comments
A3: 1 | B3: P2P | C3: 5 Ordering, Processing & Claims | D3: 5.2 Request Goods & Services | E3: 5.2.1 Create Purchase Requisition | F3: 2.1 | G3: Yes | H3: =SUM(Overview!I3:M3) -> 13 | I3: =COUNTIF('2.1'!$Q:$Q,I2) -> 1 | J3: =COUNTIF('2.1'!$Q:$Q,J2) -> 5 | K3: =COUNTIF('2.1'!$Q:$Q,K2) -> 2 | L3: =COUNTIF('2.1'!$Q:$Q,L2) -> 4 | M3: =COUNTIF('2.1'!$Q:$Q,M2) -> 1 | N3: =COUNTIF('2.1'!$P:$P,N2) -> 8 | O3: =COUNTIF('2.1'!$P:$P,O2) -> 3 | P3: =COUNTIF('2.1'!$P:$P,P2) -> 0
A4: 2 | B4: P2P | C4: 5 Ordering, Processing & Claims | D4: 5.2 Request Goods & Services | E4: 5.2.2 Release Purchase Requisition | F4: 2.2 | G4: Yes | H4: =SUM(Overview!I4:M4) -> 11 | I4: =COUNTIF('2.2'!$Q:$Q,I2) -> 1 | J4: =COUNTIF('2.2'!$Q:$Q,J2) -> 6 | K4: =COUNTIF('2.2'!$Q:$Q,K2) -> 0 | L4: =COUNTIF('2.2'!$Q:$Q,L2) -> 4 | M4: =COUNTIF('2.2'!$Q:$Q,M2) -> 0 | N4: =COUNTIF('2.2'!$P:$P,N2) -> 9 | O4: =COUNTIF('2.2'!$P:$P,O2) -> 1 | P4: =COUNTIF('2.2'!$P:$P,P2) -> 0
A5: 3 | B5: P2P | C5: 5 Ordering, Processing & Claims | D5: 5.3 Create / Place Purchase Order | E5: 5.3.1 Create Purchase Order / Order Change | F5: 3.1 | G5: Yes | H5: =SUM(I5:M5) -> 12 | I5: =COUNTIF('3.1'!$Q:$Q,I2) -> 2 | J5: =COUNTIF('3.1'!$Q:$Q,J2) -> 4 | K5: =COUNTIF('3.1'!$Q:$Q,K2) -> 2 | L5: =COUNTIF('3.1'!$Q:$Q,L2) -> 4 | M5: =COUNTIF('3.1'!$Q:$Q,M2) -> 0 | N5: =COUNTIF('3.1'!$P:$P,N2) -> 6 | O5: =COUNTIF('3.1'!$P:$P,O2) -> 5 | P5: =COUNTIF('3.1'!$P:$P,P2) -> 1
A6: 4 | B6: P2P | C6: 5 Ordering, Processing & Claims | D6: 5.3 Create / Place Purchase Order | E6: 5.3.2 Release Purchase Order | F6: 3.2 | G6: Yes | H6: =SUM(Overview!I6:M6) -> 30 | I6: =COUNTIF('3.2'!$Q:$Q,I2) -> 0 | J6: =COUNTIF('3.2'!$Q:$Q,J2) -> 10 | K6: =COUNTIF('3.2'!$Q:$Q,K2) -> 3 | L6: =COUNTIF('3.2'!$Q:$Q,L2) -> 15 | M6: =COUNTIF('3.2'!$Q:$Q,M2) -> 2 | N6: =COUNTIF('3.2'!$P:$P,N2) -> 18 | O6: =COUNTIF('3.2'!$P:$P,O2) -> 6 | P6: =COUNTIF('3.2'!$P:$P,P2) -> 5
A7: 5 | B7: P2P | C7: 5 Ordering, Processing & Claims | D7: 5.3 Create / Place Purchase Order | E7: 5.3.3 Share Purchase Order with Supplier | F7: 3.3 | G7: Yes | H7: =SUM(Overview!I7:M7) -> 12 | I7: =COUNTIF('3.3'!$Q:$Q,I2) -> 1 | J7: =COUNTIF('3.3'!$Q:$Q,J2) -> 2 | K7: =COUNTIF('3.3'!$Q:$Q,K2) -> 4 | L7: =COUNTIF('3.3'!$Q:$Q,L2) -> 4 | M7: =COUNTIF('3.3'!$Q:$Q,M2) -> 1 | N7: =COUNTIF('3.3'!$P:$P,N2) -> 9 | O7: =COUNTIF('3.3'!$P:$P,O2) -> 3 | P7: =COUNTIF('3.3'!$P:$P,P2) -> 0
A8: 6 | B8: P2P | C8: 5 Ordering, Processing & Claims | D8: 5.4 Manage Purchase Order | E8: 5.4.1 Manage Purchase Order Confirmation / Response | F8: 4.1 | G8: Yes | H8: =SUM(Overview!I8:M8) -> 7 | I8: =COUNTIF('4.1'!$Q:$Q,I2) -> 0 | J8: =COUNTIF('4.1'!$Q:$Q,J2) -> 4 | K8: =COUNTIF('4.1'!$Q:$Q,K2) -> 3 | L8: =COUNTIF('4.1'!$Q:$Q,L2) -> 0 | M8: =COUNTIF('4.1'!$Q:$Q,M2) -> 0 | N8: =COUNTIF('4.1'!$P:$P,N2) -> 1 | O8: =COUNTIF('4.1'!$P:$P,O2) -> 5 | P8: =COUNTIF('4.1'!$P:$P,P2) -> 1
A9: 7 | B9: P2P | C9: 5 Ordering, Processing & Claims | D9: 5.4 Manage Purchase Order | E9: 5.4.2 Monitor Purchase Order Status | F9: 4.2 | G9: Yes | H9: =SUM(Overview!I9:M9) -> 1 | I9: =COUNTIF('4.2'!$Q:$Q,I2) -> 0 | J9: =COUNTIF('4.2'!$Q:$Q,J2) -> 1 | K9: =COUNTIF('4.2'!$Q:$Q,K2) -> 0 | L9: =COUNTIF('4.2'!$Q:$Q,L2) -> 0 | M9: =COUNTIF('4.2'!$Q:$Q,M2) -> 0 | N9: =COUNTIF('4.2'!$P:$P,N2) -> 1 | O9: =COUNTIF('4.2'!$P:$P,O2) -> 0 | P9: =COUNTIF('4.2'!$P:$P,P2) -> 0
A10: 8 | B10: P2P | C10: 5 Ordering, Processing & Claims | D10: 5.5 Receive Goods & Services | E10: 5.5.3 Confirm Receipt of Goods & Services | F10: 5.3 | G10: No | H10: 0
A11: 9 | B11: P2P | C11: 5 Ordering, Processing & Claims | D11: 5.5 Receive Goods & Services | E11: 5.5.4 Fulfill Customs & Statutory Reporting | F11: 5.4 | G11: No | H11: 0
A12: 10 | B12: P2P | C12: 5 Ordering, Processing & Claims | D12: 5.6 Manage Quality & Returns | E12: 5.6.5 Manage Incidents, Returns & Remedies / Claims | F12: 6.5 | G12: No | H12: 0
A13: 11 | B13: P2P | F13: here
A14: 12 | B14: P2P | F14: here
H15: =SUM(H3:H14) -> 86 | I15: =SUM(I3:I14) -> 5 | J15: =SUM(J3:J14) -> 32 | K15: =SUM(K3:K14) -> 14 | L15: =SUM(L3:L14) -> 31 | M15: =SUM(M3:M14) -> 4 | N15: =SUM(N3:N14) -> 52 | O15: =SUM(O3:O14) -> 23 | P15: =SUM(P3:P14) -> 7 | Q15: =(H15-I15)/H15 -> 0.94186047
B18: Role definition
B19: Planning overview
A21: Incorporated Scenarios
A22: 1 | B22: Construction
A23: 2 | B23: OPEX-Service
A24: 3 | B24: NET Rent
A25: 4 | B25: Other

Sheet Status
A1: Status
A2: Open
A3: FIT | B3: Fit to SHERPA X Standard
A4: FIT Customizing | B4: Fit to existing SHERPA X standard, but minor customizing effort to set up basic settings for a new company code
A5: GAP Customizing | B5: Customizing needed to fulfill requirement
A6: GAP | B6: Development needed to fulfill new requirement. Approved Decision request from GF Transformation Management required
A7: N/A

Sheet Actions
A1: No | B1: Description | C1: Who | D1: Status
A2: 1
A3: 2
A4: 3
A5: 4
A6: 5
A7: 6
A8: 7
A9: 8
A10: 9
A11: 10

Sheet 2.1
A1: Requirement ID | B1: Workstream | C1: Team | D1: Polarion # | E1: Scenario | F1: Level 1 | G1: Level 2 | H1: Level 3 | I1: I as a (persona/ WHO) | J1: want to… (WHAT) | K1: Detailed Description | L1: so that… (WHY) | M1: Acceptance Criteria | N1: Notes | O1: ACN Comments | P1: Prio (DRAFT, TB FINALIZED) | Q1: Status | R1: Feature assignment | S1: Dependancy | T1: using application/3rd Party Tools/interface (HOW) | U1: Value Flow Items | V1: Master Data Items | W1: SAP Best Practice | X1: SAP Module - Core | Y1: SAP Module - Public Cloud | Z1: Functional Shift | AA1: Role, Rights & FIORI App relevance | AB1: Role in User Story | AC1: SAP Role Name | AD1: Siemens Role Name | AE1: SAP Transaction Code | AF1: Customizing Code/ ID | AG1: FIORI App ID | AH1: FIORI App Name | AI1: FIORI App Description | AJ1: FIORI App Catalog ID | AK1: Sandbox relevance | AL1: Sandbox relevance comment
A2: R-2.1.1 | H2: 5.2.1 Create Purchase Requisition_1 | I2: Requisitioner | J2: … start creating a PR by populating the required information for specific demand | K2: Req. starts creating a PR in respective system | L2: …PR can be released in S4 for further processing | M2: PR is created in S4 system and required fields are populated | Q2: FIT
A3: R-2.1.2 | H3: 5.2.1 Create Purchase Requisition_2 | I3: Requisitioner | J3: … get displayed supplier with R4B status only (if supplier is already known by the Requisitioner) | L3: … so that unqualified supplier cannot be chosen. | M3: 1.Create a PR. 2. Try to choose an unqualified supplier 3. Unqualified supplier should not be displayed | N3: 30.10-MAS: As per the email from Sven, the R4B status 16.10-MAS: Align with GF if this is already linked to the PR and PO. (Nazli or Uwe or Sven). From Source to Contract ( S2C) process | O3: What is R4B and how it is managed currently ? R4B is Ready for Business The control should come from the MDG. The system will raise messages based on the Supplier/BP status | P3: Medium | Q3: FIT
A4: R-2.1.3 | H4: 5.2.1 Create Purchase Requisition_3 | I4: Requisitioner | J4: ...order for different company codes in the same Purchasing Organisation | K4: It shall be possible to have PRs created for multiple organizations by the same user, althoug he is allocated in one spesicifc company code | L4: … I can process requisitions for different AREs within one backend. | M4: Requisitioner opens PR and can change company code/plant to desired company code/plant based on assigned authorizations. Follow on processes are based on the chosen company code/plant and not on user data | N4: 16.10-MAS: Purchasing Organization will be cross company code Porg (In Germany) + the Requisitioner should have the required Authorization to create PRs for many company codes (use Account Assignment). The POrg will be assigned to the Plants related to the germany company codes. No need to create a new Plant for Direct SRE. Plant "C300" will be use. No need to create new Company Code for Direct SRE. CoCode "3003" will be use. 15.10-MAS: Purchasing Organization will be created for SRE Direct Procurement | O4: From the Authorization point of view, the user could create PRs in many Company codes 2 Fields are Mandatory for that: - Purchasing Group - Plant --> Company Code What are the CoCode/Plants which will be in scope for the direct procurment from Germany ? - 426Q and the following 15 CoCodes | P4: High | Q4: FIT Customizing
A5: R-2.1.4 | H5: 5.2.1 Create Purchase Requisition_4 | I5: Requisitioner | J5: ... have prefilled fields | K5: Predefined fields: GR: no GR PG: Function PG GBS Invoice: Invoice required | L5: … so that quality and performance is increased. | M5: Prefilled fields, e.g. 1. GR: no GR for all SRE PRs/POs as a standard logic, instead confirmation of service delivery per workflow step 2. Purchasing Group 3. Delivery address | N5: 18.10-MAS: Default PGroup should be defined per each SAP User (from his defualt value settings or User Parameters) 16.10-MAS: There are many Account Assignments in T4Q system are we going to use them ? Check if the GR and Valuated GR checkbox are in User Parameters. Compination between the new Account Assignemnt and Item Category should be Checked --> Harish Could the default address be changed from the Plant to the Requisitioner ? 14.10-MAS: VIM Topics: Mari Kraus --> mari.kraus@siemens.com 08.10-MAS: Gergana will arrange a meeting with the VIM Team | O5: What does the PG mean ? --> Purchasing Group Defualt Values (2 Options) 1- User Parameters --> GUI 2- Defualt Values --> Fiori Apps (F1995 - Default Settings for Users) --> per user and doesn't include the GR checkbox GR and Inovice Receipt are controlled based on the Account Assignment and Item Category. Delivery Address will be by default copied from the Item line "PLant" and could be changed Service Confirmation --> is it active now in VIM ? Invoice Receiver in PR should confirm the Service Confirmation could be easly maintained via Service Entry Sheet | P5: High | Q5: GAP
A6: R-2.1.5 | H6: 5.2.1 Create Purchase Requisition_5 | I6: Requisitioner | J6: ... change prefilled data and add new data where mandratory and/or applicable . | L6: ...so that quality and performance is increased. | O6: Default values could be changed for most of the fields, unless it is not controlled by configuration --> Mainly for the Account Assignment and Item Category, which control (GR, GR Valuation, Invoice Receipt and GR-Based Invoice). There is no GL automatically determination, then the GL could be changed manually in the PO. | P6: High | Q6: FIT
A7: R-2.1.6 | H7: 5.2.1 Create Purchase Requisition_6 | I7: Requisitioner | J7: ... have the opportunity to create orders with multi-account assignment | L7: … so that services can be billed across multiple cost centers. | O7: Standard SAP behaviour. | P7: High | Q7: FIT
A8: R-2.1.7 | H8: 5.2.1 Create Purchase Requisition_7 | I8: Requisitioner | J8: ... to be able to upload attachements on header and line item level, that are stored in the S4 archiving system | L8: … so that services can be billed across multiple cost centers. | N8: 04.11-MAS: Header is not possible in SHERPAX, but Item is available 28.10-MAS: email from Markus G. "it is possible to transfer data up to 500MB. But the recommended size should not be more than 50MB". 16.10-MAS: The size of the attachement should be checked | P8: Medium | Q8: Open
A9: R-2.1.8 | H9: 5.2.1 Create Purchase Requisition_8 | I9: Requisitioner | J9: ... have the Invoice Receiver field prefilled with my GID and be able to change the prefilled invoice receiver field with a GID from SCD. Contact data of invoice receiver shall be visible on the PO Print out. | K9: Use fiels Invoice Receiver (see requirements on Z-filed "Contact person") | L9: … so that the real (technical) specialist will be visible on the PO Print out for the supplier and also he will receive the invoice in VIM | N9: Question: Check if the invoice recevier can be anyone in the company, or a user in S4P and VIM (Readsoft Successor) is required. | O9: Goods Recipient: EBKN-WEMPF For Multi-Account Assignments, multi-recipients will be available. Requisitioner: EBAN-AFNAM it is per PR line item | P9: High | Q9: GAP
A10: R-2.1.9 | H10: 5.2.1 Create Purchase Requisition_9 | I10: Requisitioner | J10: … want to be able to manually assign the required PO approvals in this step | L10: … so that I do not have to touch the PO at a later point again | O10: The user is not able to choose the Approvers of the PO in the PR creation Step PO Approver Determination will be based PO parameters (Doc Type, Company Code, POrg, PO Value) | P10: High | Q10: GAP
A11: R-2.1.10 | H11: 5.2.1 Create Purchase Requisition_10 | I11: System | J11: a budget check is run against the account assignment object to check if the planed PR volume is available in the budget | L11: … not assure than only PR aligned with the planed budget are created | M11: 1.Create a PR. 2. Try to purchase a volume bigger than the available in the buget 3. Error message occurs | N11: 18.10-MAS: Budget Control pre-requeste (Config and Master Data) should be checked on the Cost Center and WBS | O11: Depending on Controlling team, if there is a budget check on the Cost Center or WBS. Is the requiremen for a PR check through an approval process ? | P11: Medium | Q11: GAP Customizing
A12: R-2.1.11 | H12: 5.2.1 Create Purchase Requisition_11 | I12: Requisitioner/System | J12: finalize PR and check if required data is correct | K12: The PR must be completed by the requisitioner/system before PR processing can continue. | L12: …PR can be released in S4 for further processing | M12: PR enriched with information. Check if all required fields are populated | N12: 18.10-MAS: Functional Pgroup will be assigned in the PR. SAP will only check on the completion of the PR based on the Mandatory Fields. | O12: What are the required fields, Based on the SAP Standard 1- Material or Short Text are mandatory 2- Accounting Data are mandatory 3- Purchasing Org is not mandatory 4- Plant, Pgroup, Material Group are mandatory 5- Supplier nuber is not mandatory If the PGroups are defined per Buyer, then the requisitioner will assign each item to a buyer ? | Q12: FIT
A13: R-2.1.12 | H13: 5.2.1 Create Purchase Requisition_12 | I13: Process Owner | J13: I want to be able to replace a Requisitioner in case the user is not active/not applicable anymore | L13: to avoid that not active users are responsible for handling the PR and the creation/change of PO cannot be performed | O13: PR Creator --> Automatically Assigned Requisitioner --> Line Item --> Free Text and not assigned the User GID Recipent --> Line Item/Account Assignment --> Free Text and not assigned the User GID | P13: High | Q13: GAP
A14: R-2.1.13 | I14: Requisitioner | J14: want to prepare a catalogue based purchase requisition using punchout process for SRE Direct process | P14: High | Q14: FIT Customizing

Sheet 2.2
A1: Requirement ID | B1: Workstream | C1: Team | D1: Polarion # | E1: Scenario | F1: Level 1 | G1: Level 2 | H1: Level 3 | I1: I as a (persona/ WHO) | J1: want to… (WHAT) | K1: Detailed Description | L1: so that… (WHY) | M1: Acceptance Criteria | N1: Notes | O1: ACN Comment | P1: Prio (DRAFT, TB FINALIZED) | Q1: Status | R1: Feature assignment | S1: using application/3rd Party Tools/interface (HOW) | T1: Value Flow Items | U1: Master Data Items | V1: SAP Best Practice | W1: SAP Module - Core | X1: SAP Module - Public Cloud | Y1: Functional Shift | Z1: Role, Rights & FIORI App relevance | AA1: Role in User Story | AB1: SAP Role Name | AC1: Siemens Role Name | AD1: SAP Transaction Code | AE1: Customizing Code/ ID | AF1: FIORI App ID | AG1: FIORI App Name | AH1: FIORI App Description | AI1: FIORI App Catalog ID | AJ1: Sandbox relevance | AK1: Sandbox relevance comment
A2: R-2.2.1 | H2: 5.2.2 Release Purchase Requisition_1 | I2: Process Owner | J2: avoid PR approvals to the upmost extent (eg based on thresholds) | L2: so that processing time is minimized. | M2: 1. Based on detailed concept, expert approvwer to be looped in for Purchase Requsition Release or not | N2: 18.10-MAS: no need for purchase requisition approval process for SRE | O2: Expert: Is someone checking the PR data and make PR item: flexible WF has a review step + team and responsibility Management | Q2: FIT
A3: R-2.2.2 | H3: 5.2.1 Create Purchase Requisition_9 | I3: Process Owner | J3: … I do not want to have posting of goods receipt, but confirmation of service delivery per workflow step as a standard logic instead | N3: 18.10-MAS: Service Confirmation will be manage by VIM | O3: Service Confirmation --> Service Entry Sheet --> No need GR checkbox should be unchecked per line item. | P3: High | Q3: Open
A4: R-2.2.3 | H4: 5.2.2 Release Purchase Requisition_2 | I4: Expert | J4: I want to receive a notification of new PRs for approval in the system | L4: so that processing time is minimized. | M4: 1. Create a PR with expert approval step. 2. Expert receives notification. Based on detailed concept, expert approver to be looped in for Purchase Requsition Release or not | N4: This step is not required for Rel. 1410 ARE426q, however question to Sherpa X Team: Can the PR Expert Approver Step (optional) be customized based on local requirements eg. For other global Roll-outs? 21.10. G.P: it should be possible to customize this functionality on CoCo-levele | O4: To Marcus/Ajit: Who should we ask in SHERPAX Team, about the local requirement ? Standard Reports to check for the PRs without POS "F1048A - Process Purchase Requisitions" | Q4: N/A
A5: R-2.2.4 | H5: 5.2.2 Release Purchase Requisition_3 | I5: Purchaser | J5: I want to receive new PRs in my work overview (Notification via Email required) | L5: so that I can start processing the business demand. | M5: 1. PR is created. 2. Purchaser receives new PRs in their work overview. | O5: Standard SAP Reports or Fiori Apps. Standard SAP Report "ME5A" could be handelled via a Background job to run automatically. | P5: Medium | Q5: GAP
A6: R-2.2.5 | H6: 5.2.2 Release Purchase Requisition_4 | I6: Purchaser | J6: … that all PRs are automatically directed to a functional PGroup. | L6: so that PRs can be assigned to purchasers. | M6: One of the following combinations has to be selected for verification: 1. Create PR 2. Correct PGroup automatically determined according to the settings 3. Assigned purchaser(s) can see the PR in work overview | N6: All PRs are initially automatically directed to the functional GBS PGroup. GBS team then reroutes the PRs according to specific instructions (no technical set-up needed, to be manually organized and comunicated within SCM team) to personalized PR groups. | O6: The PR could be assigned to a Purchasing Group (GBS), but for the rerouting of the PR, are they changing the Purchasing Group ? What is the creitera to assign Purchasinhg Group to the PR ? | P6: High | Q6: GAP
A7: R-2.2.6 | H7: 5.2.2 Release Purchase Requisition_5 | I7: Purchaser | J7: I want to be able to reroute PRs to other Pgroups (either another functional Pgroup or personalized Pgroups) | L7: so that the requested demand are allocated to the correct purchaser | M7: 1. Open PR as a purchaser and add a line item to existing PR 2. Change Prgroup | O7: Change of Pgroup is possible in SAP Standard Fiori app: Redistribute Workload | P7: High | Q7: FIT
A8: R-2.2.7 | H8: 5.2.2 Release Purchase Requisition_6 | I8: Purchaser | J8: I want to be able to check the status of the PR and identify who is responsible for it now. | O8: Status/Item: Standard Status field is available Responsible: Purchasing Group/Item | P8: High | Q8: FIT
A9: R-2.2.8 | H9: 5.2.2 Release Purchase Requisition_7 | I9: Purchaser | J9: I want to add and delete line items | L9: so that the requested demand are allocated to the ESN | M9: 1. Open PR as a purchaser and add a line item to existing PR 2. Open PR and delete one line item | O9: Standard SAP behaviour. | P9: High | Q9: FIT
A10: R-2.2.9 | H10: 5.2.2 Release Purchase Requisition_8 | I10: Purchaser | J10: I want to be able to edit all data fields | L10: so that the quality of the PR is ensured. | M10: 1. Purchaser opens assigned PR. 2. Purchaser check all field if editable. | O10: Standard SAP behaviour. | P10: High | Q10: FIT
A11: R-2.2.10 | H11: 5.2.2 Release Purchase Requisition_9 | I11: Purchaser | J11: I want to get displayed supplier with R4B status only | L11: so that unqualified supplier cannot be chosen. | M11: 1.Create a PR. 2. Try to choose an unqualified supplier 3. Unqualified supplier should not be displayed | N11: G.P.: Create contact to Sven Stöber and IT Team | P11: High | Q11: FIT
A12: R-2.2.11 | H12: 5.2.2 Release Purchase Requisition_10 | I12: Purchaser | J12: I want to assign the PR back to the requisitioner in case of clarification incl. comment what is missing | L12: so that missing data can be filled. | M12: 1. The purchaser opens the PR. 2. Add comment and assign to requisitioner. 3. Requisitioner receives notification. 4. Requisitioner add required data and assigns back to purchaser. | O12: PR item: flexible WF has a rework request + Agent determination by BAdI for PR creator/requisitioner or SAP BTP will be used --< to be Analysed | P12: High | Q12: GAP
A13: R-2.2.12 | H13: 5.2.2 Release Purchase Requisition_11 | I13: Requisitioner | J13: I want to be notified when a PR I created is rejected | L13: so that I can initiate a clarification process, inform the business and po-tentially create a new / adjust rejected shopping basket. | M13: 1. PR rejected from expert 2. The requester receives a notification about rejection of the PR (push principle). | O13: Notification is available for if we activate the PR Flexible WF and using "My Purchase Requisitions" Note: Requisitioner/Creator should be a BP if "My Purchase Requisition" will be active. | P13: High | Q13: GAP

Sheet 3.1
A1: Requirement ID | B1: Workstream | C1: Team | D1: Polarion # | E1: Scenario | F1: Level 1 | G1: Level 2 | H1: Level 3 | I1: I as a (persona/ WHO) | J1: want to… (WHAT) | K1: Detailed Description | L1: so that… (WHY) | M1: Acceptance Criteria | N1: Notes | O1: ACN Comment | P1: Prio (DRAFT, TB FINALIZED) | Q1: Status | R1: Feature assignment | S1: using application/3rd Party Tools/interface (HOW) | T1: Value Flow Items | U1: Master Data Items | V1: SAP Best Practice | W1: SAP Module - Core | X1: SAP Module - Public Cloud | Y1: Functional Shift | Z1: Role, Rights & FIORI App relevance | AA1: Role in User Story | AB1: SAP Role Name | AC1: Siemens Role Name | AD1: SAP Transaction Code | AE1: Customizing Code/ ID | AF1: FIORI App ID | AG1: FIORI App Name | AH1: FIORI App Description | AI1: FIORI App Catalog ID | AJ1: Sandbox relevance | AK1: Sandbox relevance comment
A2: R-3.1.1 | H2: 5.3.1 Create Purchase Order / Order Change_1 | I2: Purchaser | J2: I want to be able to change PO fields to finalize input of data | L2: so that PO can be enriched with data | M2: 1. Create a PO. 2. Populate fields | O2: While converting PR to PO, fileds could be changed. Default values will be taken from PR. | P2: High | Q2: FIT
A3: R-3.1.2 | H3: 5.3.1 Create Purchase Order / Order Change_2 | I3: Purchaser | J3: I want to be able to able to upload big size attachements on header and line item level that are stored the standard archive system | L3: so that PO can be enriched with data | M3: 1. Create a PO. 2. Populate fields | N3: G.P: : to provide contact 28.10-MAS: email from Markus G. "it is possible to transfer data up to 500MB. But the recommended size should not be more than 50MB". | O3: Document Size should be checked. | P3: Medium | Q3: Open
A4: R-3.1.3 | H4: 5.3.1 Create Purchase Order / Order Change_3 | I4: Purchaser | J4: I want to be able to change payment terms which are provided / prefilled according to supplier master data | L4: so that data deviations can be handled easily. | M4: 1. Create a PO. 2. Check if payment terms and incoterms are prefilled according to entries in supplier master data. | O4: Payment terms will not be inserted in the PR. Default value from Supplier master could be changed. | P4: High | Q4: FIT
A5: R-3.1.4 | H5: 5.3.1 Create Purchase Order / Order Change_4 | I5: Purchaser | J5: I want that relevant data is replicated to the Siemens Data Cloud | L5: so that official Siemens PO/PVO reportings are supported. | M5: PO data is available in PO/PVO reportings. | O5: Marcus: xBT Data Management team is driving connection between S/4 and SDC under the Data Governance Framework. | P5: High | Q5: FIT
A6: R-3.1.5 | H6: 5.3.1 Create Purchase Order / Order Change_5 | I6: Purchaser | J6: have an overview of new POs to be created from the PR | L6: so that processing time is minimized. | M6: PO Overview of new POs to be created and not to copy PR number from previous step | O6: Do you mean a report for the PRs which have not been converted to POs ? If yes, Standard Reports are availbale. "F1048A - Process Purchase Requisitions" | P6: Medium | Q6: FIT
A7: R-3.1.6 | H7: 5.3.1 Create Purchase Order / Order Change_6 | I7: Purchaser | J7: ... to be able to forward a PO to an Expert Buyer for review and change of the PO | L7: so that a high quality of the PO is assured | M7: 1. Create a PO with expert approval step. 2. Expert receives notification. Based on orgnisational set-up, expert approver to be looped in for PO Release or not | O7: Flexible WF: you could forward it as an email or add a new optional step for Expert Review. | P7: High | Q7: FIT Customizing
A8: R-3.1.7 | H8: 5.3.1 Create Purchase Order / Order Change_7 | I8: Expert (Buyer) | J8: .. To receive an email with the respective PO work item to review | L8: so that processing time is minimized. | M8: 1. Create a PO with expert approval step. 2. Expert receives notification. Based on orgnisational set-up , expert approver to be looped in for PO Release or not | O8: Flexible WF: Notification will be sent by defualt in "My Inbox" Fiori App after creating the Purchase Order. Email option is also available. | P8: Low | Q8: FIT Customizing
A9: R-3.1.8 | H9: 5.3.1 Create Purchase Order / Order Change_8 | I9: Expert (Buyer) | J9: .. To be able to review, change all data, send back and/or confirm PO | L9: so that a high quality of the PO is assured | M9: 1. Create a PO with expert approval step. 2. Expert receives notification. Based on detailed concept, expert approver to be looped in for PO Release or not | O9: Change the PO fields is available by accessing the Purchase Order Change transaction and if the change will affect the Total PO price the workflow will be retriggerred. Send back for review is not available in the Flexible WF. | P9: High | Q9: GAP
A10: R-3.1.9 | H10: 5.3.1 Create Purchase Order / Order Change_9 | I10: Expert (Buyer) and/or Purchaser | J10: I want to get closed multiple POs via mass update final invoice flag | L10: so that the open POs in the system can be closed (fiscal year ending). | M10: 1. Provide a list of line item number PO number of e.g. POs, where PO final invoice flag to be set 2. User / admins with respective authorization conduct the mass up-date. 3. Check POs are updated correctly. | N10: TBD if this functionaliyt is required for SRE ARE426q and if yes, who will have the rights to üerform mass updates? | O10: F2593 - Mass Changes to Purchase Orders Authorization to be requested to buyers - Currently available only for "Emergency Access (IT)" | P10: Medium | Q10: GAP
A11: R-3.1.10 | H11: 5.3.1 Create Purchase Order / Order Change_11 | I11: Process Owner | J11: I want that purchaser will be actively notified when negative deviations between PO price and invoice price occurs (price is higher than a defined tolerance) | L11: so that the PO can be adjusted. | M11: 1. Create a PO. 2. Post the invoice with large deviations so that the price is higher than a defined tolerance. 3. Check if the purchaser receives a pus notification. | N11: TBD if this functionaliyt is required for SRE ARE426q | O11: VIM -- consulidated topic for VIM meeting Tolerance will be configured in SAP. | P11: Medium | Q11: Open
A12: R-3.1.11 | H12: 5.3.1 Create Purchase Order / Order Change_13 | I12: Purchaser | J12: I want to have the possibility to update multiple POs via a mass update option without approval required | L12: so that reorganizations of data can be updated, e.g. accounting el-ements, G/L accounts. | M12: 1. Create multiple Pos. 2. Provide a list of POs and data fields which should be updated, e.g. PO old G/L account à G/L account PO old accounting element to new element 3. Execute mass update. 4. Check if changes are displayed in the POs. | N12: TBD if this functionaliyt is required for SRE ARE426q | O12: Is possible, If the changed field is not subject of Workflow reset. F2593 - Mass Changes to Purchase Orders Authorization to be requested to buyers - Currently available only for "Emergency Access (IT)" | P12: Medium | Q12: GAP
A13: R-3.1.12 | H13: 5.3.1 Create Purchase Order / Order Change_14 | I13: Process Owner | J13: I want to be able to replace a Requisitioner in case the user is not active/not applicable anymore | L13: to avoid that not active users are responsible for handling the PO and the creation/change of PO cannot be performed | N13: TBD if this functionaliyt is required for SRE ARE426q | O13: Requisitioner filed is a free text filed and could be changed. To have more control on this field additional logic should be performed. Initialy the Requisitioner should be the PR creator, but could be changed Requisitioner is on item level and the first line item will be the main requisitioner for the whole PR --> a logic to check the active user | P13: High | Q13: GAP

Sheet 3.2
A1: Requirement ID | B1: Workstream | C1: Team | D1: Polarion # | E1: Scenario | F1: Level 1 | G1: Level 2 | H1: Level 3 | I1: I as a (persona/ WHO) | J1: want to… (WHAT) | K1: Detailed Description | L1: so that… (WHY) | M1: Acceptance Criteria | N1: Notes | O1: ACN Comment | P1: Prio (DRAFT, TB FINALIZED) | Q1: Status | R1: Feature assignment | S1: using application/3rd Party Tools/interface (HOW) | T1: Value Flow Items | U1: Master Data Items | V1: SAP Best Practice | W1: SAP Module - Core | X1: SAP Module - Public Cloud | Y1: Functional Shift | Z1: Role, Rights & FIORI App relevance | AA1: Role in User Story | AB1: SAP Role Name | AC1: Siemens Role Name | AD1: SAP Transaction Code | AE1: Customizing Code/ ID | AF1: FIORI App ID | AG1: FIORI App Name | AH1: FIORI App Description | AI1: FIORI App Catalog ID | AJ1: Sandbox relevance | AK1: Sandbox relevance comment
A2: R-3.2.1 | H2: 5.3.2 Release Purchase Order_1 | I2: System | J2: … want to route the PO to the required PO approvals based on the choice provided by the Requisitioner in the PR creation step. | L2: so that the PR is not send again back to the Requisitioner | O2: The approver selection will be based on the information which have been copied from the PR, and if the Purchaser changed it. Purchasing Organization Purchasing Group | P2: High | Q2: GAP
A3: R-3.2.2 | H3: 5.3.2 Release Purchase Order_1 | I3: PO Approver | J3: I want to receive an email when new POs for approval arise | L3: so that I do not have to check proactively the system for new POs. | M3: 1. Create PO where an expert approval is required. 2. Check if PO expert receives a push notification for PO approval. | O3: Flexible WF: Notification will be sent by defualt in "My Inbox" Fiori App. Email option is also available. | P3: High | Q3: FIT Customizing
A4: R-3.2.3 | H4: 5.3.2 Release Purchase Order_2 | I4: PO Approver | J4: I want to edit relevant data fields in the PO, if required | L4: so that I can send the PO for approval and further processing is ensured. | M4: 1. Open the PO in the expert work overview. 2. Check if relevant data fields are editable. 3. Approve the PO. | O4: Changes will not be through "My Inbox" app. If the approver has access the Purchase Order Change transaction authorization, then he could perform the changes. | P4: Medium | Q4: FIT
A5: R-3.2.4 | H5: 5.3.2 Release Purchase Order_15 | I5: PO Approver | J5: I want to able to maintain substitutes | O5: Available in "My Inbox" Fiori app. Authorization for the substitute is required. | P5: High | Q5: FIT
A6: R-3.2.5 | H6: 5.3.2 Release Purchase Order_17 | I6: PO Approver | J6: I want to approve via smartphone, tablet or computer and all necessary data for decision are provided | L6: so that I can minimize the processing time. | M6: 1. Create multiple POs. 2. Check the opportunity for approval for tablet, computer and smartphone. 3. All relevant data are correctly displayed for decision. 4. Check if the POs can be approved and rejected via smartphone, tablet or computer. | O6: Not available for the Procureemnt Process in SHERPAX but could be activated | P6: Low | Q6: GAP
A7: R-3.2.6 | H7: 5.3.2 Release Purchase Order_19 | I7: PO Approver | J7: I want that the entire PO is rejected if an approver rejects the PO | L7: so that a PO is processed as a whole. | M7: 1. Create a PO with multiple approvers. 2. One approver rejects the PO. 3. Check if the PO has status “rejected”. 4. Check if work items from other approvers disappears. | O7: Standard SAP behaviour. PO is approved on Header Level. | P7: Medium | Q7: FIT
A8: R-3.2.7 | H8: 5.3.2 Release Purchase Order_21 | I8: PO Approver | J8: I want to approve all line items in a PO (which are assigned to me) with one click | K8: Use case 1: A PO with different accounting types, one cost center line item 1 - asset - cost center 1 and line item 2 - cost center - cost center 1 Use case 2: different cost centers, one approver line item 1 - cost center 1 - approver 1 and line item 2 - cost center 2 - approver 1 | L8: so that processing time in minimized | M8: 1. Create a PO with the following data Use case 1: A PO with different accounting types, one cost center line item 1 - asset - cost center 1 and line item 2 - cost center - cost center 1 Use case 2: different cost centers same approver line item 1 - cost center 1 - approver 1 and line item 2 - cost center 2 - approver 1 2. Check if the approver is correctly assigned. 3. Check if the approver can approve all item with one click. | N8: TBD if ARE426Q has the use case of multiple PO approvers | O8: Standard SAP behaviour. PO is entirelly approved on Header Level. Flexible WF: Starting Condition currently for Cost Center or Project - With SAT interface only one cost center will be sent to SAT to get the approvers --> in Buzias, the cost center in the first line item is selected. | P8: Medium | Q8: GAP
A9: R-3.2.8 | H9: 5.3.2 Release Purchase Order_3 | I9: Asset Expert | J9: I want to be involved in the PO expert verification step in case of - usage of the asset accounting type - or when the price per unit for goods is above a defined threshold | L9: so that the correctness of the asset process is ensured. | M9: 1. Create a PO with asset accounting type. 2. Asset expert involved in expert verification step. 1. Create a PO for goods with unit price above defined threshold. 2. Asset expert involved in expert verification step.G57 | N9: TBD Asset creation process for ARE426Q to be checked with dimitrios.chortikoglou@siemens.com G.P.: Fixed asset process is not required for ARE 426Q. Catalogue items should be ordered through Punch out process | O9: Asset Account Assignment is not an option in the Flexible WF starting Condition. Price Threshold could be defined in the Flexible WF starting Condition. | Q9: N/A
A10: R-3.2.9 | H10: 5.3.2 Release Purchase Order_4 | I10: Asset Expert | J10: I want to be able to edit accounting elements and asset master data | L10: so that the correctness of the asset process is ensured. | M10: 1. Create a PO with asset accounting type. 2. Asset expert involved in expert verification step. 3. Asset expert can edit the PO. 1. Create a PO for goods with unit price above defined threshold. 2. Asset expert involved in expert verification step. 3. Asset expert can edit the PO. | N10: TBD Asset creation process for ARE426Q to be checked with dimitrios.chortikoglou@siemens.com G.P.: Fixed asset process is not required for ARE 426Q. Catalogue items should be ordered through Punch out process | O10: Account Assignment could be chnaged during the approval process. | Q10: N/A
A11: R-3.2.10 | H11: 5.3.2 Release Purchase Order_5 | I11: Purchaser | J11: I want the system to check if the delivery date is in the past before final approval. Send back PO to Purchaser if delivery date is in the past. | L11: so that supplier receives the correct delivery date. | M11: 1. Create a PO. 2. Before final approval check if delivery date is in the past | O11: Delivery Date checking required opening the PO to check the messages. Approver could share any information from "My Inbox" app with the requisitioner. | P11: Low | Q11: GAP
A12: R-3.2.11 | H12: 5.3.2 Release Purchase Order_6 | I12: Purchaser | J12: I want that the language of the PO printout corresponds to the language of supplier master data (If language not applicable: use English as default) | L12: so that miscommunication towards the supplier can be avoided. | M12: 1. Create POs for several suppliers with different languages. 2. Check if the PO printout language is the correct supplier language. | O12: SHERPAX template follow the same. Predefined texts should include the vendor language. The Vendor Language in the PO will be the main driver, and it will be defualted from the vendor master. | P12: High | Q12: FIT
A13: R-3.2.12 | H13: 5.3.2 Release Purchase Order_7 | I13: Purchaser | J13: I want to have copy stored in the system of the PO printout as soon as it is created for legal aspects | L13: so that a copy of for legal purposes is stored in the system. | M13: 1. Create a PO. 2. Check if a copy of the PO printout is stored as attachment in the system. 3. Create a supplier relevant PO change. 4. Check if the PO change is stored as attachment in the system. | O13: All print out will be saved and attached to the PO. | P13: High | Q13: FIT
A14: R-3.2.13 | H14: 5.3.2 Release Purchase Order_8 | I14: Purchaser | J14: I want to rename the PO printout from “Order” to “Order Change” in case adjustments in the PO are required | L14: so that miscommunication towards the supplier can be avoided. | M14: 1. Create PO 2. Change in PO supplier relevant data 3. Check printout if “Order Change” is visible 4. Check printout if all line items are visible | O14: NB: (1) New --> Purchase Order (2) Change --> Change To FO: (1) New --> Framework Order (2) Change --> Change To | P14: High | Q14: FIT
A15: R-3.2.14 | H15: 5.3.2 Release Purchase Order_8 | I15: Purchaser | J15: I want to rename the PO printout from “Order” to “Order information” in case this is not a binding PO | L15: so that miscommunication towards the supplier can be avoided. | M15: 1. Create PO 2. Change in PO supplier relevant data 3. Check printout if “Order information” is visible 4. Check printout if all line items are visible | N15: TBD if PO Type Framework + item cat. B (Limit) can be set per default as Order Information, meaning not binding PO. | O15: Binding PO --> without specific Service in the line item, but only limit. What if the PO has many line item, one with limit and the other with Service. --> not a case Printout Form Titel is based on the Document type. | P15: High | Q15: GAP
A16: R-3.2.15 | H16: 5.3.2 Release Purchase Order_9 | I16: Purchaser | J16: I want that PO printout form contains automated texts and these be adjusted based on local (legal) requirements | L16: so that local (legal) regulations are fulfilled. | M16: 1. Create PO for different legal entities and languages 2. Check if content is correctly displayed | O16: Text changes are based on Company Code Purchasing Org Purchasing Group Order Type | P16: High | Q16: GAP
A17: R-3.2.16 | H17: 5.3.2 Release Purchase Order_10 | I17: Purchaser | J17: I want that PO is transferred according to the output media setting in the PO (prefilled from supplier master data) | L17: so that the PO is transferred as agreed with the supplier. | M17: 1. Create several POs with different output media settings - EDI (Classic EDI, SupplyON, or other future platforms) - Email - Fax (roll-In activity) - No output, if transfer is suppressed 2. Check if the PO transfer to the supplier worked correctly. | O17: It will be based on the Printout Condition Records Printout Condition type: "Y005" | P17: High | Q17: FIT Customizing
A18: R-3.2.17 | H18: 5.3.2 Release Purchase Order_11 | I18: Purchaser | J18: I want to decide if a PO change should be sent to supplier | L18: so that the supplier receives only a “PO Change” document if changed data fields are relevant for them. | M18: 1. Create a PO. 2. Change the PO. 3. Mark the PO “to be sent to the supplier” 4. Check if the PO is sent to the supplier 5. Mark the PO “not be sent to supplier” 6. Check if the PO is not sent to supplier | N18: G.P to merge the two requirements R-3.2.17 and R-3.2.18, this requirement will be only for sending or not sending the PO to supplier | O18: Is this a current functionality ? If, yes. How do you manage it ? Changes will be on assigned messages to the PO and the change will be manually per each PO. | P18: High | Q18: FIT
A19: R-3.2.18 | H19: 5.3.2 Release Purchase Order_12 | I19: Purchaser | J19: I want to select an alternative email to whom the Po should be sent | L19: so that POs for internal purposes are not sent to the supplier. | M19: 1. Create a PO. 2. Mark the PO „not to be sent“. 3. Check if the PO is not sent to the supplier. | N19: 04.11-MAS: Add another requirement to send the PO only to a buyer , R-3.2.18 could be used | P19: High | Q19: GAP Customizing
A20: R-3.2.19 | H20: 5.3.2 Release Purchase Order_13 | I20: Purchaser | J20: I want Requisitioner to receive a copy of a PO when a PO is sent to supplier via EDI or email | L20: so that Requisitioner knows the PO is sent to supplier (Requisitioner wants to have a copy of PO) | M20: Copy Requisitioner when Purchaser emails the PO to supplier | O20: Requisitioner field is a free text --> From where should we got the contact email. | P20: Low | Q20: GAP
A21: R-3.2.20 | H21: 5.3.2 Release Purchase Order_14 | I21: Purchaser | J21: PO is approved according the Siemens regulations and Sherpa X Standard | L21: so that the PO Approver is automatically addressed (if required) | M21: Interface with SAT is required | O21: Interface should be used with the Flexible WF to get the Authorized person for approval based on the PO Value Limit. SAT is based on 10 levels and Company Code Cost Center Profit Center Approval level Role (Functional and Commercial) Current interface logic for Buzias has been build with 2 levels Below 50K and Above 50K If the flexible WF will be only 2 levels approval (Functional and Commercial) with 50K thr | P21: High | Q21: GAP
A22: R-3.2.21 | H22: 5.3.2 Release Purchase Order_15 | I22: Purchaser | J22: I want to edit rejected POs | L22: so that I can avoid creating a new PO. | M22: 1. Create a PO. 2. Reject a PO. 3. The purchaser opens a rejected PO and edits the PO. 4. The PO is sent for approval (again). | O22: Available in SHERPAX, Change the rejected PO and then the Flexible WF will be retriggered. | P22: High | Q22: FIT
A23: R-3.2.22 | H23: 5.3.2 Release Purchase Order_16 | I23: Purchaser | J23: I want that only approvers with an activated user account approve POs | L23: so that the identity of user was verified. | M23: 1. Create a PO where an approver without active user account has to approve. 2. Check if the approver cannot access and approve. | O23: In Flexible WF, it will be defined by the SAP User ID and if the approver has and SAP ID then he/she is active. Additional checks on User profile (if he didn't access SAP for a long time or he is not a Siemens Employee) then it will be a gap. | P23: Low | Q23: GAP
A24: R-3.2.23 | H24: 5.3.2 Release Purchase Order_17 | I24: Purchaser | J24: I want to edit POs which are currently in the approval step | L24: so that I can correct errors without restarting the process. | M24: 1. Create a PO and start the approval step. 2. The purchaser calls and edits the PO. 3. During the “PO edit mode” the work item for approval should disappear in the approval step. 4. After editing the PO, the PO is again in the approval step. | O24: PO could be changed in approval process, only Total price could restart the workflow Standard fields which could be added: Header level attributes: Company Code Purchasing Group Purchasing Organization Total Net Order Value --> already selected Incoterms Currency Item level attributes: Material Group Outline Agreement Plant | P24: Medium | Q24: FIT
A25: R-3.2.24 | H25: 5.3.2 Release Purchase Order_18 | I25: Requisitioner | J25: I want to receive a push notification with a comment if the respective PO of my PR is rejected | L25: so that process time is minimized. | M25: 1. Create a PO. 2. Reject a PO with reason for rejection (reason is mandatory). 3. Check if requisitioner receives a notification incl. reason for rejection. | O25: GUI/Fiori reports could be used. Notifications to be checked | P25: Low | Q25: GAP
A26: R-3.2.25 | H26: 5.3.2 Release Purchase Order_19 | I26: Requisitioner | J26: I want that possible PO approvers are determined automatically | N26: TBD - Create approval matrix per ESN, PO value and Cost center logic | O26: PO Approvers will be determined automatically in the background. Cost Center is not in the Responsibility Definition. PO value will controlle the Flexible WF or SAT | P26: High | Q26: GAP
A27: R-3.2.26 | H27: 5.3.2 Release Purchase Order_20 | I27: Process owner | J27: I want that the next level of approver applies in case of no determination of an approver in a lower range of value I want that the workflow responsible gets notified in case no approver is determined | L27: so that processing time for approvals can be minimized. | M27: 1. Create a PO where the value range is not maintained. 2. Check if the next approval level applies. 3. Create a PO where no approver is maintained (e.g. new cost cen-ters) 4. Check if the workflow responsible gets notified. | N27: 28.10-MAS: changes will be on Buzias approval enhancement | O27: Value Levels: This will be based on SAT interface Approval Steps: Functional and Commercial both should be approved Workflow Admin should monitor the WF steps and redirect the WF-Steps without an approver assigned | P27: High | Q27: GAP
A28: R-3.2.27 | H28: 5.3.2 Release Purchase Order_21 | I28: As a requisitioner and approver | J28: we want get notified on a regular basis, if a PO is not approved in a specific time frame | L28: so that processing time can be minimized. | M28: 1. Create a PO with status “in approval”. 2. Wait until the time frame set is overdue (x days). 3. Check if a LoA approver receives a reminder notification. | N28: 28.10-MAS: for the Approver is required but for requisitioner is a nice to have. SRE will use the standard template without changes. | O28: Flexible WF: Deadline config Will appear in "My Inbox" and "Manage Purchase Order" apps | P28: Medium | Q28: GAP Customizing
A29: R-3.2.28 | H29: 5.3.2 Release Purchase Order_22 | I29: As a requisitioner, purchaser and approver, | J29: we want to be able to add “adhoc” approvers manually in the approval process, | L29: so that approvers required can be involved. | M29: 1. Valid maybe also for PR 2. Challenge how could a requisitioner do this? 3. Only user with respective authorizations should available as adhoc approvers | O29: Flexible WF: approvers are automatically determined without any additional approvers added Substitution or Forward options could be used Not Standard in SAP to have an adhoc approving step | P29: High | Q29: GAP
A30: R-3.2.29 | H30: 5.3.2 Release Purchase Order_23 | I30: As a requisitioner, purchaser and approver, | J30: we want to be able to replace approvers manually in approval process, according to LoA authorizations a) If no approvers could be determined a fallback or dummy ap-prover should be chosen b) Existing approver is currently not available | L30: so that approval process can be fastened. | M30: 1. Search for a PO. 2. Open the PO and replace the existing approver. | N30: 28.10-MAS: Team and Responsibility management will be used to limit the approvers based on their responsibility and it will work in the backgroung. Cost Center and WBS are not in the standard Responsibility definition. | O30: Substitute option could be perfomred per each approver BP is required per each approver | Q30: GAP
A31: R-3.2.30 | H31: 5.3.2 Release Purchase Order_24 | I31: As a requisitioner, purchaser and approver, | J31: we want to be able to replace approvers manually in approval process, according to LoA authorizations a) If no approvers could be determined a fallback or dummy ap-prover should be chosen b) Existing approver is currently not available | L31: so that approval process can be fastened. | M31: 1. Search for a PO. 2. Open the PO and replace the existing approver. | O31: Duplicate with the above | Q31: N/A
A32: R-3.2.31 | H32: 5.3.2 Release Purchase Order_25 | I32: Process owner | J32: I want to ensure that same PO approver cannot perform two approvals for one PO | K32: Commercial and technical PO approvers should be different people | L32: so that the approval is according to regulations. | M32: 1. Create PO with two LoA approval steps. 2. Determine one approver for two approval steps. 3. An error message appears. | O32: Controlled by approver determination logic + Teams Fucntion/Role If SAT is added, then additional logic should be added to do this check | P32: High | Q32: GAP
A33: R-3.2.32 | H33: 5.3.2 Release Purchase Order_26 | I33: Process owner | J33: I want only defined changes need an approval | L33: so that time is not wasted on the approval of uncritical data fields. | M33: 1. Create a PO. 2. Approve a PO. 3. Change multiple fields in the PO. 4. Check that workflow is only be started for changes to critical data fields. | O33: Currently setting for NB and FO --> Flexible WF will be restarted for Total Net Value change Standard fields which could be added: Header level attributes: Company Code Purchasing Group Purchasing Organization Total Net Order Value --> already selected Incoterms Currency Item level attributes: Material Group Outline Agreement Plant | P33: Medium | Q33: FIT Customizing
A34: R-3.2.33 | H34: 5.3.2 Release Purchase Order_27 | I34: Process owner | J34: I want all newly added line items in a PO to restart the approval of the entire PO | L34: so that local regulations are fulfilled. | M34: 1. Create a PO. 2. Approve a PO. 3. Add a new line item to the PO. 4. Check if the PO approval process has been started. | O34: Currently available | P34: High | Q34: FIT

Sheet 3.3
A1: Requirement ID | B1: Workstream | C1: Team | D1: Polarion # | E1: Scenario | F1: Level 1 | G1: Level 2 | H1: Level 3 | I1: I as a (persona/ WHO) | J1: want to… (WHAT) | K1: Detailed Description | L1: so that… (WHY) | M1: Acceptance Criteria | N1: Note | O1: ACN Comment | P1: Prio (DRAFT, TB FINALIZED) | Q1: Status | R1: Feature assignment | S1: using application/3rd Party Tools/interface (HOW) | T1: Value Flow Items | U1: Master Data Items | V1: SAP Best Practice | W1: SAP Module - Core | X1: SAP Module - Public Cloud | Y1: Functional Shift | Z1: Role, Rights & FIORI App relevance | AA1: Role in User Story | AB1: SAP Role Name | AC1: Siemens Role Name | AD1: SAP Transaction Code | AE1: Customizing Code/ ID | AF1: FIORI App ID | AG1: FIORI App Name | AH1: FIORI App Description | AI1: FIORI App Catalog ID | AJ1: Sandbox relevance | AK1: Sandbox relevance comment
A2: R-3.3.1 | H2: 5.3.3 Share Purchase Order with Supplier_1 | I2: Process owner | J2: I want to have the Invoice Receiver data displayed in the PO printout and EDI on header level. Email and phone number available. | K2: By default, the Requisitioner is the Invoice recipient, but the Requisitioner can change this in PR | L2: so that clarifications can be processed faster. | M2: 1. Create a PO. 2. Open a PO printout and check if technical contact is correctly dis-played. 3. Create a PO with EDI. 4. Open the EDI message and check if technical contact is correctly dis-played. | N2: 28.10-MAS: It should be in header and replace the contact person. In addition other information should be added (email + Telephone number) from the User Profile | O2: Item Level and are not a mandatory fields Requisitioner --> EBAN-AFNAM --> Item Recipient --> EBKN-WEMPF --> Account Assignment The Recipient (Invoice Receiver) will be printed on the item level. If we have many Item with Different Recipient --> Each line item will have a separate printed Recipient If the user GID has been enterred correctly and the user has an SAP User ID, then his User Name will appear in the print out | P2: High | Q2: GAP
A3: R-3.3.2 | H3: 5.3.3 Share Purchase Order with Supplier_2 | I3: Process owner | J3: I want that the invoice address is derived and displayed correctly on the PO printout and transferred in the EDI segments | L3: so that invoices coming from the supplier are addressed correctly. | M3: 1. Create PO for an EDI connected supplier. 2. Check PO printout if the invoice address is correctly displayed. 3. Check EDI message if data is in correct segments. | N3: 28.10-MAS: EDI require more analysis | O3: Invoice Address will be predefined Text and will be on header level based on Company Code Purchase Org Pgroup Doc Type | P3: High | Q3: FIT Customizing
A4: R-3.3.3 | H4: 5.3.3 Share Purchase Order with Supplier_3 | I4: Process owner | J4: I want that the correct invoice email and POC (purchase order confirmation) address are derived and displayed correctly on the PO printout and transferred cor-rectly in the EDI segments | L4: so that invoices from supplier will be addressed correctly (in case of email and POR are addressed to the desired email address). | M4: 1. Create a PO for an EDI connected supplier. 2. Check in the PO printout if both email addresses are correctly dis-played. 3. Check EDI message if data is in the correct segments. | O4: Pre-defined Text: The correct email address will be determined based on Company Code Purchasing Org Purchasing Group Order Type Correction is a configuration task, PO header texts could be use to print additional information. | P4: High | Q4: FIT Customizing
A5: R-3.3.4 | H5: 5.3.3 Share Purchase Order with Supplier_4 | I5: Process owner | J5: I want that for all countries where tax rates is required in the PO, tax rates are correctly determined | L5: so that tax regulations apply. | M5: 1. Create PO for a tax relevant country. 2. Check PO, PO printout and EDI message if tax rates are correct determined. | N5: Tax Team - Max Roesch N/A for DE CoCo | O5: Tax determination will be followed based on the Finance configuration | Q5: N/A
A6: R-3.3.5 | H6: 5.3.3 Share Purchase Order with Supplier_5 | I6: Process owner | J6: I want that for all countries where withholding tax is required in the PO that withholding tax is correctly determined | L6: so that tax regulations apply. | M6: 1. Create PO for a tax relevant country. 2. Check withholding tax in PO. | N6: Refer to new WHT Standard SX Process for Rel 1320.WHT Team - Ali S. CF T | O6: Withholding tax will be followed based on the Finance configuration | P6: High | Q6: FIT Customizing
A7: R-3.3.6 | H7: 5.3.3 Share Purchase Order with Supplier_6 | I7: Process owner | J7: I want for all countries where VAT ID is required in the PO that the VAT ID is correctly determined | L7: so that tax regulations apply. | N7: Tax Team - Max Roesch N/A for DE CoCo | O7: VAT ID determination will be based on the Business Partner and will be printed in the PO printout | P7: Medium | Q7: FIT
A8: R-3.3.7 | H8: 5.3.3 Share Purchase Order with Supplier_7 | I8: Purchaser | J8: I want to have my contact data displayed on PO printout and EDI message | L8: so that the supplier can contact purchaser in case of clarifications. | M8: Create a PO and compare the PGroup data with the address of the PO printout. | O8: Purchse Order Creator --> Name and data (from User Profile) Purchasing Group --> Name and data (from configuration) Purchasing Group per each buyer will be configured | P8: High | Q8: FIT Customizing
A9: R-3.3.8 | H9: 5.3.3 Share Purchase Order with Supplier_8 | I9: Purchaser | J9: I want to decide if a PO change should be sent to supplier and the changes to be highlighted | L9: so that the supplier receives only a “PO Change” document if changed data fields are relevant for them. | M9: 1. Create a PO. 2. Change the PO. 3. Mark the PO “to be sent to the supplier” 4. Check if the PO is sent to the supplier 5. Mark the PO “not be sent to supplier” 6. Check if the PO is not sent to supplier | N9: 28.10-MAS: Check if the PO changes will be highlighted to the supplier to identify the changes | O9: Purchaser could manage the output message per each PO. Automatically message condition will be determined based on the created condition record. The purchaser could change the determined printing condition or add a new one. The purchased controlls, if the output message will be sent to the supplier after saving the PO or not | P9: Medium | Q9: Open
A10: R-3.3.9 | H10: 5.3.3 Share Purchase Order with Supplier_9 | I10: Purchaser | J10: I want that attachments in the PO marked as “external” should be sent to supplier (email, EDI) | L10: so that the supplier receives all relevant information. | M10: 1. Create a PO incl. attachments. Mark the PO as “external” for email transfer. 2. Create a PO incl. attachment. Mark the PO as “external” for EDI transfer. 3. Check the email sent to the supplier if attachments are included. 4. Check the EDI message to the supplier if attachments are included. | N10: 28.10-MAS: config should be performed to activate the functionality | P10: Medium | Q10: GAP Customizing
A11: R-3.3.10 | H11: 5.3.3 Share Purchase Order with Supplier_10 | I11: Purchaser | J11: I want to decide (manually) if a PO should be sent to supplier (invoice already received from the supplier) | L11: so that POs for internal purposes are not sent to the supplier. | M11: 1. Create a PO. 2. Mark the PO „not to be sent“. 3. Check if the PO is not sent to the supplier. | O11: Purchaser could manage the output message per each PO. | P11: High | Q11: FIT
A12: R-3.3.11 | H12: 5.3.3 Share Purchase Order with Supplier_12 | I12: Requisitioner | J12: I want to be able to add a contact for any kind of content inquiries from supplier | K12: as technical contact in case of inquiry of supplier | L12: so that clarifications can be processed faster. | M12: 1. Create a PO. 2. Open a PO printout and check if technical contact is correctly dis-played. 3. Create a PO with EDI. 4. Open the EDI message and check if technical contact is correctly dis-played. | N12: 28.10-MAS: The requirment here is for the Receipient (Invoice Receiver) to be copied from the PR to PO and then printed. By defualt it will be printed from the PR to the PO and will be printed per line item. If it will be printed on header level, then a custome logic should be implemented | O12: PO header text could be used for additional data | P12: High | Q12: GAP
A13: R-3.3.12 | J13: Blocker: PO Print out shall contain the Contract ID | P13: High | Q13: GAP
A14: R-3.3.13 | J14: Blocker: PO Print out shall contain the Guarantees | P14: High | Q14: GAP

Sheet 4.1
A1: Requirement ID | B1: Workstream | C1: Team | D1: Polarion # | E1: Scenario | F1: Level 1 | G1: Level 2 | H1: Level 3 | I1: I as a (persona/ WHO) | J1: want to… (WHAT) | K1: Detailed Description | L1: so that… (WHY) | M1: Acceptance Criteria | N1: Notes | O1: ACN Comment | P1: Prio (DRAFT, TB FINALIZED) | Q1: Status | R1: Feature assignment | S1: using application/3rd Party Tools/interface (HOW) | T1: Value Flow Items | U1: Master Data Items | V1: SAP Best Practice | W1: SAP Module - Core | X1: SAP Module - Public Cloud | Y1: Functional Shift | Z1: Role, Rights & FIORI App relevance | AA1: Role in User Story | AB1: SAP Role Name | AC1: Siemens Role Name | AD1: SAP Transaction Code | AE1: Customizing Code/ ID | AF1: FIORI App ID | AG1: FIORI App Name | AH1: FIORI App Description | AI1: FIORI App Catalog ID | AJ1: Sandbox relevance | AK1: Sandbox relevance comment
A2: R-4.1.1 | H2: 5.4.1 Manage Purchase Order Confirmation_4 | I2: Process owner | J2: I want the POR (Purchase Order Response) process to be implemented as per Sherpa X Standard | L2: so that manual effort is avoided. | O2: Order Aknowledgement could be selected per each line item Vendor Confirmation Flexible WF is active for NB document type but not for FO | P2: High | Q2: FIT Customizing
A3: R-4.1.2 | H3: 5.4.1 Manage Purchase Order Confirmation_1 | I3: Purchaser | J3: I want to receive PORs with deviations beyond tolerances in my work overview. These are automatically identified by the system by comparing EDI POR with the PO | L3: so that deviations can be clarified, and the purchaser can accept or reject the POR. | M3: 1. Create a PO. 2. Create a POR with deviation beyond tolerances. 3. Check if the POR appears in the purchaser’s work overview and if deviations are displayed correctly. 4. The purchaser accepts the POR and has the possibility to decide if a PO change should be sent to supplier. 5. After acceptance the POR is maintained in PO. 6. The PO date fields are updated with the POR data. | N3: 28.10-MAS: check the Toleramces | O3: Tolerances: Price --> No tolerance Delivery date --> under confirmation key Quantity --> Require Purchasing Info Record PO creator could receive notification in his "Myinbox" app to approve the vendor data | P3: Medium | Q3: FIT Customizing
A4: R-4.1.3 | H4: 5.4.1 Manage Purchase Order Confirmation_2 | I4: Purchaser | J4: I want to receive PORs with deviations within tolerances in my work overview. These are automatically identified by the system by comparing EDI POR with the PO | L4: so that deviations can be clarified, and the purchaser can accept or reject the POR. | M4: 1. Create a PO. 2. Create a POs with different deviations within tolerances. 3. Check if the POR is automatically maintained in the PO. 4. Check if the PO data field are updated with the respective POR data. 5. Check if the deviations are predefined to be sent to supplier, and of the PO change is sent to supplier. 6. Check if the deviations are predefined NOT to be sent to supplier, and the PO change is NOT sent to the supplier. | O4: Automatically Approved. Vendor Confirmation Reports could be used. | P4: Medium | Q4: FIT
A5: R-4.1.4 | H5: 5.4.1 Manage Purchase Order Confirmation_3 | I5: Purchaser | J5: I want that PORs without deviation are stored in the system automatically in the dedicated field in the PO | L5: so that I can see the status “POR sent”. | M5: 1. Create a PO. 2. Create a POR without price deviations. 3. Check if the POR is documented in the dedicated field. 4. Check if the PO change is NOT sent to the supplier. | O5: there is a special tab for venor confirmation | P5: Medium | Q5: FIT
A6: R-4.1.5 | H6: 5.4.1 Manage Purchase Order Confirmation_4 | I6: Process owner | J6: I want to define tolerances (lower value and higher value) for dedicated data fields (e.g. price, delivery date) | L6: so that manual effort is avoided. | M6: Check if tolerances can be maintained from an administrator. | O6: Current System: any change of the price will be consider as a change beyon the tolerance. Delivery Data: is a configuration activity. Current Confirmation Keys: Y002 "GR without Inbound Delivery" Y003 "Indirect Confirmation" | P6: Low | Q6: FIT Customizing
A7: R-4.1.6 | H7: 5.4.1 Manage Purchase Order Confirmation_5 | I7: Purchaser | J7: I want in the case that an existing POR which is not processed yet becomes invalid, when a new and updated POR sent from the supplier arise | L7: so that misunderstandings with the supplier can be avoided. | M7: 1. Create a PO. 2. Create a POR. 3. Create an updated POR. 4. Check if the unprocessed POR is in the purchaser’s work overview. 5. Check if the old POR is replaced by the new one. | N7: 28.10-MAS: Provide cases: If SRE receives a confirmation after an already approved or rejected confirmation . | O7: Not possible, if we receive a supplier confirmtaion with approval status. The the new one will not be created. | P7: Medium | Q7: FIT
A8: R-4.1.7 | H8: 5.4.1 Manage Purchase Order Confirmation_6 | I8: Purchaser | J8: I want that a POR with a partially confirmation of the PO only relies to the respective line item so that unconfirmed line items stay untouched | L8: so that errors can be avoided. | M8: 1. Create a PO with multiple line items. 2. Create a POR only for one litem. 3. Approve the POR. 4. Check if line item of the POR is updated. 5. Check if the remaining PO line items are untouched from POR. | P8: Medium | Q8: FIT

Sheet 4.2
A1: Requirement ID | B1: Workstream | C1: Team | D1: Polarion # | E1: Scenario | F1: Level 1 | G1: Level 2 | H1: Level 3 | I1: I as a (persona/ WHO) | J1: want to… (WHAT) | K1: Detailed Description | L1: so that… (WHY) | M1: Acceptance Criteria | N1: Notes | O1: ACN Comment | P1: Prio (DRAFT, TB FINALIZED) | Q1: Status | R1: Feature assignment | S1: using application/3rd Party Tools/interface (HOW) | T1: Value Flow Items | U1: Master Data Items | V1: SAP Best Practice | W1: SAP Module - Core | X1: SAP Module - Public Cloud | Y1: Functional Shift | Z1: Role, Rights & FIORI App relevance | AA1: Role in User Story | AB1: SAP Role Name | AC1: Siemens Role Name | AD1: SAP Transaction Code | AE1: Customizing Code/ ID | AF1: FIORI App ID | AG1: FIORI App Name | AH1: FIORI App Description | AI1: FIORI App Catalog ID | AJ1: Sandbox relevance | AK1: Sandbox relevance comment
A2: R-4.2.1 | H2: 5.4.2 Monitor Purchase Order Status_1 | I2: Requisitioner and Purchaser | J2: ...see an overview of the latest status of PR from the follow-on documents in S/4 - status of PR, - status of PO(s), - GR(s), - invoices with documents - payment status - PO closed status | K2: Transparency shall be given based on the initial PRs created by the Requisitioner for follow-up documents (via my PRs) | L2: ...I can use S/4 to check the current status of the “open” requisitions or search for closed POs. | M2: 1. The requisitioner sees the new PRs requiring processing in their overvire in S4 2. The requisitioner sees open PRs in their overview in S4. Definition of open: Final invoice flag not yet set in PO. 3. Search function option for closed PRs / POs. 4. PR status overview related to entire process should contain: - New PRs - Open PRs (related to entire process) - POs created - POs approved - GRs booked (optional) - Invoices received - Invoices paid | N2: 28.10-MAS: Provide a list of reports | O2: Standard Reprots (GUI and Fiori) are available to monitor the statues for PRs and POs | P2: High | Q2: FIT

Sheet 5.3
A1: Workstream | B1: Team | C1: Polarion # | D1: Scenario | E1: Level 1 | F1: Level 2 | G1: Level 3 | H1: I as a (persona/ WHO) | I1: want to… (WHAT) | J1: Detailed Description | K1: so that… (WHY) | L1: Acceptance Criteria | M1: Notes | N1: Feature assignment | O1: using application/3rd Party Tools/interface (HOW) | P1: Value Flow Items | Q1: Master Data Items | R1: SAP Best Practice | S1: SAP Module - Core | T1: SAP Module - Public Cloud | U1: Functional Shift | V1: Role, Rights & FIORI App relevance | W1: Role in User Story | X1: SAP Role Name | Y1: Siemens Role Name | Z1: SAP Transaction Code | AA1: Customizing Code/ ID | AB1: FIORI App ID | AC1: FIORI App Name | AD1: FIORI App Description | AE1: FIORI App Catalog ID | AF1: Sandbox relevance | AG1: Sandbox relevance comment

Sheet 5.4
A1: Workstream | B1: Team | C1: Polarion # | D1: Scenario | E1: Level 1 | F1: Level 2 | G1: Level 3 | H1: I as a (persona/ WHO) | I1: want to… (WHAT) | J1: Detailed Description | K1: so that… (WHY) | L1: Acceptance Criteria | M1: Notes | N1: Feature assignment | O1: using application/3rd Party Tools/interface (HOW) | P1: Value Flow Items | Q1: Master Data Items | R1: SAP Best Practice | S1: SAP Module - Core | T1: SAP Module - Public Cloud | U1: Functional Shift | V1: Role, Rights & FIORI App relevance | W1: Role in User Story | X1: SAP Role Name | Y1: Siemens Role Name | Z1: SAP Transaction Code | AA1: Customizing Code/ ID | AB1: FIORI App ID | AC1: FIORI App Name | AD1: FIORI App Description | AE1: FIORI App Catalog ID | AF1: Sandbox relevance | AG1: Sandbox relevance comment

Sheet 6.5
A1: Workstream | B1: Team | C1: Polarion # | D1: Scenario | E1: Level 1 | F1: Level 2 | G1: Level 3 | H1: I as a (persona/ WHO) | I1: want to… (WHAT) | J1: Detailed Description | K1: so that… (WHY) | L1: Acceptance Criteria | M1: Notes | N1: Feature assignment | O1: using application/3rd Party Tools/interface (HOW) | P1: Value Flow Items | Q1: Master Data Items | R1: SAP Best Practice | S1: SAP Module - Core | T1: SAP Module - Public Cloud | U1: Functional Shift | V1: Role, Rights & FIORI App relevance | W1: Role in User Story | X1: SAP Role Name | Y1: Siemens Role Name | Z1: SAP Transaction Code | AA1: Customizing Code/ ID | AB1: FIORI App ID | AC1: FIORI App Name | AD1: FIORI App Description | AE1: FIORI App Catalog ID | AF1: Sandbox relevance | AG1: Sandbox relevance comment

Sheet Z Fields
A1: PR Field - EBAN | B1: EN - Description | C1: DE - Description | D1: Siemens Data Tab | E1: Value Table | F1: In PO (Y-N) | G1: In PO form (Y-N) | H1: Comment | I1: Status | J1: SHERPAX Used In | K1: Standard Field | L1: Functionaloity | M1: Intergation | N1: Requirement ID | O1: Z-Field is required in SHERPAX (Y-N) | P1: Accenture Team Comments In PO (Y-N) | Q1: Accenture Team Comments In PO form (Y-N) | R1: Siemens Functionality | S1: Comments
F2: Please check if Z Field Should be in PO. Put Yes or No | G2: Please add Yes, if we need this information on the Print Layout. Else No. | O2: Please add Yes, if the field is Mandatory for the SHERPAX and we can't disable it. Else No. | R2: Please add information about Functionality of this field. How is it used? | S2: Please add any additional Comments about fields.
A3: ZZZTERM | B3: Terms of Payment | C3: Zahlungsbedingung | D3: Lieferung/Rechnung | F3: Yes | G3: Yes | H3: The Payment terms will not be available in PR. It will be maintaned directly in the PO. It will be printed in the PO Form (The Payment Term Description) | I3: FIT | J3: PO - Header | K3: EKKO-ZTERM | L3: Copied to PO Standard field | M3: I2P | P3: Yes, but question about translation. Example: PO 4500003193, YINT-Before End of the month Due net (SUPL) -> in PO form "bis zum Ende des Monats ohne Abzug" | Q3: Yes, question about translation. Example: PO 4500003193, YINT-Before End of the month Due net (SUPL) -> in PO form "bis zum Ende des Monats ohne Abzug" | R3: - | S3: Replace Z Field with Standard S4 Field based on PO Type (if applicable), otherwise it is required
A4: ZZKDATB | B4: Validity Per. Start | C4: Laufzeitbeginn | D4: Lieferung/Rechnung | E4: Date | F4: Yes | G4: Yes | H4: Start date is used for As-Is SJ-Sonstige Jahresbest document type and will be replaced by FO document type. Start date will be avaibale in PR-FO line item and will be copied to PO-FO. | I4: FIT | J4: PR - Line item PO - Header | K4: EBAN-STARTDATE EKKO-KDATB | L4: Copied to PO Standard field | P4: Yes | Q4: Yes | R4: - | S4: Replace Z Field with Standard S4 Field based on PO Type (if applicable), otherwise it is required
A5: ZZKDATE | B5: Validity Period End | C5: Laufzeitende | D5: Lieferung/Rechnung | E5: Date | F5: Yes | G5: Yes | H5: End date is used for As-Is SJ-Sonstige Jahresbest document type and will be replaced by FO document type. End date will be avaibale in PR-FO line item and will be copied to PO-FO. | I5: FIT | J5: PR - Line item PO - Header | K5: EBAN-ENDDATE EKKO-KDATE | L5: Copied to PO Standard field | P5: Yes | Q5: Yes | R5: - | S5: Replace Z Field with Standard S4 Field based on PO Type (if applicable), otherwise it is required
A6: ZZBEDAT | B6: Document Date | C6: Belegdatum | D6: Lieferung/Rechnung | E6: Date | F6: Yes | G6: Yes | H6: Purchase Order creation date could identified with ME5A. Field Automatically filled with PO creation data in PO and an enhancement is running on MP1 to copy it in PR | I6: FIT | J6: PO - Header | K6: EKKO-AEDAT | L6: Report | P6: Yes | Q6: Yes, but it is date of Document EKKO - BEDAT. This date could be modified by users | R6: Date of PO creation, relevant for reporting | S6: Replace Z Field with Standard S4 Field based on PO Type (if applicable), otherwise it is required
A7: ZZGID | B7: Contact person GID | C7: Ansprechpartner-GID (Line Item) | D7: General | F7: Yes | G7: - | H7: As-Is: The field is mantained in PR line item will is copied to PO Z-field in Header. To-Be: Service Confirmation in VIM workflow | L7: PO printout | M7: I2P | N7: R-2.1.8 | P7: Possible insert in Text as variant | Q7: NA | R7: Added in PR by Requestor Name of contact person, who acts as invoice recipient and can differ from the requestor ; Contact person perosonal information is avaialable on PO Print out (not Requestor information!) | S7: 2. To be replaced by Invoice Receiver (WAREN-EMPF - Empfänger) as standard field in S4 2. All users from SCD - no predefined user list required? 3. Contact for supplier on the PO Print out
A8: ZZMBE_PARTNER | B8: Contact person | C8: Ansprechpartner (Header OrgID) | F8: Yes | G8: Yes | H8: As-Is: This is the PO header field, which is used for PO Print out (Contact Person) and Invoice Receiver | L8: PO printout | N8: R-3.3.1 | P8: Yes | Q8: Yes, but Person is "Created By" if empty then Purchasing Group name | R8: Name of contact person, who acts as invoice recipient and can differ from the requestor; Contact person perosonal information is avaialable on PO Print out (not Requestor information!) | S8: 1. To be replaced by Invoice Receiver (WAREN-EMPF - Empfänger) as standard field in S4 2. All users from SCD - no predefined user list required? 3. Contact for supplier on the PO Print out
A9: AFNAM | B9: Requestor | C9: Anforderer (Line item) | F9: - | G9: - | H9: Standard SAP field which is in the PR and PO. Will be automatically transfered to the PO from the reference PR. As requested to be by default equal to the PR creator | L9: Notification | N9: R-3.2.24 | P9: Need to check | Q9: NA | S9: TBD: It must be ensured that the same person is always set as the requester in each position (possible error message when creating the order if there is a difference at position level)
A10: ZZBSART | B10: Order Type | C10: Bestellart | D10: OrgDaten | E10: T161 | F10: No | G10: Yes | H10: Define the PO document type, which will be created from the PR. Purchaser will select the correct PO doc type manually. The link between the PR and PO will be conrolled by the SHERPAX configured document types refrences. | I10: FIT | J10: PO - Header | K10: EKKO-BSART | L10: Copied to PO Standard field | P10: No | Q10: No, check with BT Products | R10: SRE-specific PO Types. | S10: Based on PO naming a difference between mandatory and non-mandatory PO should be visible on the PO printout in the title (for example Order and Order information)
A11: ZZEBELN | B11: Purchasing Document | C11: Einkaufsbeleg | D11: OrgDaten | E11: EKKO | F11: Yes | G11: No | H11: PO document numbers which have been created with the PR-item as reference will be automatically updated in the PR. PO texts will be copied from the PR based on SHERPAX copying rules. | I11: Not Required | P11: Yes, PO type visiable in PO | Q11: NA | R11: Relevant for amendments, includes the PO number of the order that is extended by the respective PR (as a new item). Automatic adjustment of the PO volume + automatic generation of PO texts. | S11: Replace Z Field with Standard S4 Field based on PO Type (if applicable), otherwise it is required Check PO adjustment process and what is the link to the existing PO
A12: ZZM_VERTRAGSID | B12: Contract ID | C12: Vertrags ID | D12: General | E12: Free | F12: Yes | G12: Yes | H12: The Contract ID will not be available in PR. It will be maintaned directly in the PO-Your Reference Field (12 digit) and will be printed in PO print Form. As-Is: the field is copied to PO Z-field in the header to be printed | L12: PO printout | N12: R-3.3.12 | P12: Check after BT Products | Q12: Check with BT Products | R12: Reference in the PO to framework agreements If populated, a text with the ID of the framework agreement is automatically generated on the PO printout and is therefore visible to the supplier. Contract ID is taken from SCM STAR (manually). Contract check is no longer used | S12: Storage of contracts directly in S4 System possible? To discuss with Simon regarding future implementation S2C
A13: ZZRS_GUARANTY_C | B13: Guarantees | C13: Vertragserfüllungsbürgschaft | D13: Bürgschaft | E13: Checkbox | F13: Yes | G13: Yes | L13: PO printout - Text Control | M13: I2P | N13: R-3.3.13 | P13: Check after BT Products | Q13: Check with BT Products | R13: Tracking of guarantees; payment blocks possible if guarantees are not available | S13: Procurement negotiates security performance During project execution, this information must be available and addressed during final acceptance. Tool support to ensure that the invoice cannot be fully paid if it is not clarified whether a security retention or a guarantee is in place. In the case of a guarantee, release of the security retention and process handover to Accounting. Tracking of the guarantee until receipt and “booking” (recording data so that new personnel can quickly find the data even 5 years later). Refer to pptx
A14: ZZRS_GUARANTY_W | B14: Guarantees | C14: Gewährleistungsbürgschaft | D14: Bürgschaft | E14: Checkbox | F14: Yes | G14: Yes | L14: PO printout - Text Control | M14: I2P | N14: R-3.3.13 | P14: Check after BT Products | Q14: Check with BT Products
A15: ZZM_X_SECURITY | B15: Guarantees | C15: Immer Sicherheitseinbehalt | D15: General | E15: Checkbox | F15: Yes | G15: Yes | L15: PO printout - Text Control | M15: I2P | N15: R-3.3.13 | P15: Check after BT Products | Q15: Check with BT Products
A16: ZZM_PROJECT | B16: Projekt | C16: Projekt | D16: General | E16: ZSRE_MM_MBA_CPRJ | F16: No | G16: No | I16: Not Required | P16: SRE checking | Q16: SRE checking
A17: ZZM_X_EMAIL | B17: E-Mail to Buyer | C17: E-Mail an Einkäufer | D17: General | E17: Checkbox | F17: Yes | G17: No | L17: Notification | N17: R-3.2.18 | P17: Need to check | Q17: NA | R17: Buyer receives an e-mail when PO is sent | S17: No need of the specific field, biut rather the functionality
A18: YYBAULS | B18: Building contract | C18: Bauleistung | D18: OrgDaten | E18: Yes - No | F18: No | G18: Yes | I18: Open | L18: PO printout - Text Control | M18: I2P | N18: R-3.3.14 | P18: NA | Q18: Not clear | R18: If YES, the selected supplier must have a valid exemption certificate filed in SAP -> Verification of the exemption certificate in MDG at the PR level & ReadSoft. Deduction of Tax if certificate not available Automatic generation of order texts. | S18: New process in SX Rel. 1220/1320, check of exemption certificate is performed upon invoice receiving and only for specific ESNs as pre PO. Refer to slides 18-21 WHT. PO Print out to be extended (Functionality is availabe, need to be customized), contact Ali
A19: ZZVERSART | B19: Dispatch type | C19: Versandart | D19: OrgDaten | E19: YYM02 | F19: No | G19: Yes | I19: Open | L19: PO printout - Text Control | P19: NA | Q19: Check with BT Products | R19: Triggers automatic generation of text on the PO print out with reference to Siemens Terms & Conditions based on the ordered service/goods (general, construction, design service etc.) | S19: No need of the specific field, biut rather the functionality
A20: YYECLASS | B20: eCl@ss | C20: eCl@ss | D20: General | F20: No | G20: No | I20: Not Required
A21: ZZM_EFFORT_TM | B21: Abrechnungsart | C21: Abrechnungsart | D21: General | E21: Fixed Values | F21: No | G21: No | I21: Not Required
A22: ZZM_HEBEL | B22: Hebel | C22: Hebel | D22: General | E22: ZSRE_MM_MBA_CHBL | F22: No | G22: No | I22: Not Required
A23: ZZM_BUDGET | B23: Vergabe zu Budget | C23: Vergabe zu Budget | D23: General | E23: Free | F23: No | G23: No | I23: Not Required
A24: ZZWOID | B24: Workorder ID | C24: Workorder ID | D24: General | E24: Free | F24: No | G24: No | I24: Not Required
A25: ZZEHS_RELEVANT | B25: EHS relevant | C25: EHS relevant | D25: General | E25: Yes - No | F25: No | G25: No | I25: Not Required
A26: ZZZEKE | B26: Condition rate | C26: Konditionsbetrag - Einkaufserfolg NES | D26: General | E26: Free | F26: No | G26: No | I26: Not Required

Sheet PO Types
B2: Process | C2: Planned or Unplanned | D2: PO Doc type | E2: Item Category | F2: Acc Assignmt | G2: Validity Date | H2: Item Product Type | I2: Quantity | J2: Unit Price | K2: Limit | L2: Good/Service Receipt | M2: Non-Valuated GR | N2: Invoice Receipt | O2: GR-Based Invoice Verification | P2: DRAFT | Q2: DRAFT
B3: Consumption | C3: Planned | D3: NB - Standard | E3: - Standard | F3: K – Cost Center A - Asset P – Project | G3: NA | H3: NA | I3: Yes | J3: Yes | K3: No | L3: Optional | M3: Optional | N3: Yes | O3: Optional | P3: SV - Normal PO with ref. to contract SN - Normal PO with no ref. to offer | Q3: Autom. Text - nicht änderbar Die Bestellung erfolgt zu unseren jeweils gültigen Bestellbedingungen, sofern nicht in dieser Bestellung auf abweichende Bedingungen verwiesen wird, die dann vorrangig gelten. Die Bestellbedingungen können Sie unter https://www.siemens.com/de/de/unternehmen/konzern/konzernfunktionen/supply-chain-management/zusammenarbeit-mit-siemens.html einsehen. Auf Wunsch werden wir Ihnen diese auch gerne zusenden. Manuell Einkäufer verweist im Kopftext auf die spezifische BB
B4: Consumption | C4: Unplanned | D4: NB - Standard | E4: B – Limit * | F4: K – Cost Center | G4: NA | H4: NA | I4: No (1 AU) | J4: No | K4: Yes | L4: NA | M4: NA | N4: Yes | O4: NA | Q4: Autom. Text - nicht änderbar Die Bestellung erfolgt zu unseren jeweils gültigen Bestellbedingungen, sofern nicht in dieser Bestellung auf abweichende Bedingungen verwiesen wird, die dann vorrangig gelten. Die Bestellbedingungen können Sie unter https://www.siemens.com/de/de/unternehmen/konzern/konzernfunktionen/supply-chain-management/zusammenarbeit-mit-siemens.html einsehen. Auf Wunsch werden wir Ihnen diese auch gerne zusenden. Manuell Einkäufer verweist im Kopftext auf die spezifische BB
B5: Framework | C5: Planned | D5: FO - Framework | E5: - Standard | F5: K – Cost Center A - Asset P – Project | G5: Header Start and End Date | H5: NA | I5: Yes | J5: Yes | K5: No | L5: Optional | M5: Optional | N5: Yes | O5: Optional | P5: SJ - Binding Framework order with ref. to contract | Q5: Autom. Text - nicht änderbar Die Bestellung erfolgt zu unseren jeweils gültigen Bestellbedingungen, sofern nicht in dieser Bestellung auf abweichende Bedingungen verwiesen wird, die dann vorrangig gelten. Die Bestellbedingungen können Sie unter https://www.siemens.com/de/de/unternehmen/konzern/konzernfunktionen/supply-chain-management/zusammenarbeit-mit-siemens.html einsehen. Auf Wunsch werden wir Ihnen diese auch gerne zusenden. Manuell Einkäufer verweist im Kopftext auf die spezifische BB. Verweis auf VertragsID (Standardfeld?)
B6: Framework | C6: Unplanned | D6: FO - Framework | E6: B – Limit * | F6: K – Cost Center | G6: Header Start and End Date | H6: NA | I6: No (1 AU) | J6: No | K6: Yes | L6: NA | M6: NA | N6: Yes | O6: NA | P6: UJ - Non-binding Framework order with ref. to contract | Q6: Bestellinformation Autom. Text - nicht änderbar Die Bestellung erfolgt zu unseren jeweils gültigen Bestellbedingungen, sofern nicht in dieser Bestellung auf abweichende Bedingungen verwiesen wird, die dann vorrangig gelten. Die Bestellbedingungen können Sie unter https://www.siemens.com/de/de/unternehmen/konzern/konzernfunktionen/supply-chain-management/zusammenarbeit-mit-siemens.html einsehen. Auf Wunsch werden wir Ihnen diese auch gerne zusenden. Manuell Einkäufer verweist im Kopftext auf die spezifische BB. Verweis auf VertragsID (Standardfeld?) Diese Bestellinformation ist rechtlich unverbindlich und dient nur zur Information über den voraussichtlichen Bedarf an Lieferungen und Leistungen innerhalb des Geltungszeitraumes der Bestellinformation.
B7: Lean Service | C7: Planned | D7: NB - Standard | E7: - Standard | F7: K – Cost Center A - Asset P – Project | G7: Item Start and End Date | H7: Yes – 2-Service | I7: Yes | J7: Yes | K7: No | L7: Optional | M7: Optional | N7: Yes | O7: Optional | P7: TBD
B8: Lean Service | C8: Unplanned | D8: NB - Standard | E8: E- Enhanced Limit | F8: K – Cost Center P - Project A - Asset | G8: Item Start and End Date | H8: Yes – 2-Service | I8: No | J8: No | K8: Yes | L8: Yes | M8: No | N8: Yes | O8: Yes | P8: TBD

Sheet Planning Overview
A1: Feature assignment # | B1: Feature Description | C1: Wave - Sprint
C2: Epic ID Polarion | D2: Capability ID Polarion | E2: Feature ID Polarion
A3: 1 | B3: SX_GF_P2P_P2R_Manage Purchase Requisition | C3: SX-20956 | D3: SX-42305
A4: 2 | B4: SX_GF_P2P_P2R_Manage Purchase Order | C4: SX-20956 | D4: SX-42305
A5: 3 | B5: SX_GF_P2P_P2R_Workflow Setup & SAT Integration | C5: SX-20956 | D5: SX-42305
A6: 4 | B6: SX_GF_P2P_P2R_Email Notifications & Reminders & Alerts | C6: SX-20956 | D6: SX-42305
A7: 5 | B7: SX_GF_P2P_P2R_PO Output & PO Response & PO Change | C7: SX-20956 | D7: SX-42305
A8: 6 | B8: SX_GF_P2P_P2R_Fields specific Requirements | C8: SX-20956 | D8: SX-42305
A9: 7 | B9: SX_GF_P2P_P2R_Reporting | C9: SX-20956 | D9: SX-42305
A10: 8 | B10: SX_GF_P2P_P2R_Rollout Phases | C10: SX-20956 | D10: SX-42305
A11: 9

Sheet Role Definition
A1: Role | B1: Description | C1: S4 | D1: User Group
A2: Requisitioner | B2: Processes Purchase Requisitions (PR) | C2: Requisitioner | E2: Person in a Siemens entity who has a demand and creates or arranges the creation of a purchase requisition in the order processing system. The requisitioner defines the technical and logistic requirements of the demand.
A3: Expert (Synonym: Process Owner) | B3: Involved in predefined use cases in PR or PO to validate and update data for dedicated purpose (EHS expert, asset accounting...) | C3: Expert | E3: Person who is fulfilling neither financial approval nor signature mandate on behalf of the company. People from different departments check various governance functions, e.g. Tax, Customs, Compliance, asset, other accounting details
A4: Purchaser | B4: Processes PR and creates PO, Order Confirmations and Claims/Returns | C4: Purchaser | E4: Person who carries out the operational purchasing transactions.
A5: Approver | B5: Approves POs based on a signature mandate | C5: Approver | D5: managers with a signature authorization mandate | E5: Responsibility of the approval step with the person having the knowledge. Person who has been appointed an authorized signatory for approval, either internally (USB) and/or externally (executive authority). The principle of two independent signatures shall be maintained. A person may be granted both internal and external authority.
A6: Buyer | B6: Executes buying activities (eg retrieves quotes from supplier, determines sources), could act as an Expert predefined use cases in PR or PO to validate and update data for dedicated purpose | C6: Strategic Buyer | D6: SCM Procurement employees or mandated people based on Commodity assignment | E6: Strategic purchaser and local contact for Requisitioner in relation to all purchasing topics and the entire purchasing process.

Sheet Parking_Lot
F1: Process steps
A2: Story # | B2: Workstream | C2: Team | D2: Polarion # | E2: Scenario | F2: Level 1 | G2: Level 2 | H2: Level 3 | I2: Level 4 | J2: I as a (persona/ WHO) | K2: want to… (WHAT) | L2: Detailed Description | M2: so that… (WHY) | N2: using application/3rd Party Tools/interface (HOW) | O2: Acceptance Criteria | P2: Value Flow Items | Q2: Master Data Items | R2: SAP Best Practice | S2: SAP Module - Core | T2: SAP Module - Public Cloud | U2: Functional Shift | V2: Notes
B3: P2R Indirect Business Purpose | C3: P2R | D3: SX-xxxx - to be added later | E3: Catalogue/ EPR Demands for Goods | F3: Ordering, processing, and claims | G3: Request Goods & Services | H3: Create Purchase Requisition | J3: Requisitioner | K3: I want to get an overview of the suppliers delivery performance and an alerting, if known delivery problems were reported for this supplier | M3: so that I can choose another supplier if the delivery performance is too low for my needs | O3: 1. Create a PR. 2. Get the supplier delivery performance.
B4: P2R Indirect Business Purpose | C4: P2R | D4: SX-xxxx - to be added later | E4: Catalogue/ EPR Demands for Goods | F4: Ordering, processing, and claims | G4: Create / Place Purchase Order | H4: Share Purchase Order with Supplier | J4: As a purchaser, | K4: I want that the PO printout contains required data and a local design | M4: so that local regulations about content and guideline for design are ful-filled. | O4: Purchaser opens the PO and checks the layout and required data.
B5: P2R Indirect Business Purpose | C5: P2R | D5: SX-xxxx - to be added later | E5: Catalogue/ EPR Demands for Goods | F5: Ordering, processing, and claims | G5: Request Goods & Services | H5: Create Purchase Requisition | J5: As a requisitioner, | K5: I want to edit the PR via smartphone and tablet (if required) | M5: so that I can minimize the throughput time. | O5: 1. Create multiple PRs. 2. Check if the PR is editable via tablet. 3. Check if the PR is editable via smartphone.
B6: P2R Indirect Business Purpose | C6: P2R | D6: SX-xxxx - to be added later | E6: Catalogue/ EPR Demands for Goods | F6: Ordering, processing, and claims | G6: Receive Goods & Services | H6: Confirm Receipt of Goods & Services | J6: As a process owner, | K6: I want that invoices for trusted partner are paid without GR / performance receipt booking | M6: so that a lean processing time can be ensured. | O6: 1. Create a PO with a trusted partner. 2. Create an invoice without deviations. 3. Invoice is paid without GR / performance receipt booking. | V6: Two-way-match (price, quantity) applies.
B7: P2R Indirect Business Purpose | C7: P2R | D7: SX-xxxx - to be added later | E7: Catalogue/ EPR Demands for Goods | F7: Ordering, processing, and claims | G7: Receive Goods & Services | H7: Confirm Receipt of Goods & Services | J7: As a process owner, | K7: I want to to have a two-way match for catalog/ EPR requisitions | M7: so that the invoice payment is faster in execution and reducing effort for requisitioners | O7: 1. Create a PR with GR expected. 2. Create a PO. 3. Post invoice. 4. Check if requsitioner receives a webcycle for missing GR. 5. Book GR 6. Create a PR without GR expected. 7. Create a PO. 8. Post invoice. 9. Check if requistioner receives a webcycle for performance receipt.
B8: P2R Indirect Business Purpose | C8: P2R | D8: SX-xxxx - to be added later | E8: Catalogue/ EPR Demands for Goods | F8: Ordering, processing, and claims | G8: Receive Goods & Services | H8: Confirm Receipt of Goods & Services | J8: As a process owner, | K8: I want to define the rules for preset if a GR is expected or not, based on ESN and /or UoM = AU | M8: so that desired GR or performance receipt process will be triggered | O8: 1. Create PR with UoM = AU. 2. Check if GR expected flag is not set. 3. Create PR with UoM unequal AU. 4. Check if GR expected flag is set 5. Create PR with a service ESN. 6. Check if GR expected is not set. 7. Create PR with a non service ESN. 8. Check if GR expected is set.
B9: P2R Indirect Business Purpose | C9: P2R | D9: SX-xxxx - to be added later | E9: Catalogue/ EPR Demands for Goods | F9: Ordering, processing, and claims | J9: Requisitioner | K9: ...the structure of the myMall shopping basket to be carried over into S/4 | L9: I cannot add or delete line items in PR. If the PR needs to be changed, the requisitioner must reject the PR in S/4 and a create a new one in myMall. The structure of the PR cannot be changed by simply adding new line items or deleting existing line items. | M9: …information relayed from the backend to myMall is consistent with the origin shopping basket and the PO status can be checked. | N9: S4 | O9: 1. If requisitioner tries to delete line item in PR, no possibility is offered. 2. If requisitioner tries to add line item, no possibility offered. 3. Deletion of entire PR is possible. | V9: Priority: low
B10: P2R Indirect Business Purpose | C10: P2R | D10: SX-xxxx - to be added later | E10: Catalogue/ EPR Demands for Goods | F10: Ordering, processing, and claims | J10: Requisitioner | K10: ...add or delete line items in PR. | L10: If the PR needs to be changed, the requisitioner must reject the PR in S/4 and a create a new one in myMall. The structure of the PR cannot be changed by simply adding new line items or deleting existing line items. | M10: …information relayed from the backend to myMall is consistent with the origin shopping basket and the PO status can be checked. | N10: S4 | O10: 1. Requisitioner opens PR and he is able to delete line item in PR 2. Requisitioner opens PR and he is able to add line item in PR 3. Deletion of entire PR is possible. | V10: Priority: low
B11: P2R Indirect Business Purpose | C11: P2R | D11: SX-xxxx - to be added later | E11: Catalogue/ EPR Demands for Goods | F11: Ordering, processing, and claims | J11: Requisitioner | K11: ...change prefilled data and I want to add mandatory data which are not prefilled. | L11: Only a subset of mandatory information are transferred into the PR and need to be adjusted/ added on demand | M11: ...the PR is correct for further processing. | N11: S4 | O11: Edit prefilled data fields, e.g. 1. Account assignment category, accounting element 2. Delivery address Edit empty data fields, e.g. 1. G/L Account | V11: Priority: medium
B12: P2R Indirect Business Purpose | C12: P2R | D12: SX-xxxx - to be added later | E12: Catalogue/ EPR Demands for Goods | F12: Ordering, processing, and claims | J12: Requisitioner | K12: ...process activities in my local language | L12: Processing steps shall be displayed in local language on the UI | M12: ...I can fully understand what data is required. | N12: S4 | O12: After backend login system language is in the desired language.
B13: P2R Indirect Business Purpose | C13: P2R | D13: SX-xxxx - to be added later | F13: Ordering, processing, and claims | J13: Requisitioner | K13: ...want to have mixed shopping baskets transferred from myMall automat-ically split into order types | L13: Related Order types in a Shopping Cart shall be split into different PRs | M13: ...specific follow-on processes can be initiated. | N13: S4 | O13: Requisitioner see in PR overview up to 3 PRs depending on amount of different order types in myMall shopping basket. 1. All catalog line items and easy price request line items are visible in one PR. 2. All limit line items are visible in one PR. 3. All free text line items are visible in one PR. | V13: Priority: high
B14: P2R Indirect Business Purpose | C14: P2R | D14: SX-xxxx - to be added later | E14: Catalogue/ EPR Demands for Goods | F14: Ordering, processing, and claims | J14: As a requisitioner, | K14: I want to decide if a GR is expected or not | M14: so that the desired GR or performance receipt process will be triggered. | O14: 1. Create a PR with GR expected. 2. Create a PO. 3. Post invoice. 4. Check if requsitioner receives a webcycle for missing GR. 5. Book GR 6. Create a PR without GR expected. 7. Create a PO. 8. Post invoice. 9. Check if requistioner receives a webcycle for performance receipt.
B15: P2R Indirect Business Purpose | C15: P2R | D15: SX-xxxx - to be added later | E15: Services | F15: Ordering, processing, and claims | J15: Requisitioner | K15: ...want to be able to generate mass PRs (on a yearly basis) via upload or interface (actually based on Excel) | M15: no manual effort for PR creation | N15: Upload functionality based
B16: P2R Indirect Business Purpose | C16: P2R | D16: SX-xxxx - to be added later | E16: Catalogue/ EPR Demands for Goods | F16: Ordering, processing, and claims | J16: Requisitioner | K16: ...want to suppress (via a flag) price and quantity from the PO printout | M16: ...price and quantity are not displayed in the PO printout sent to the supplier. | N16: S4 | O16: Acceptance Criteria 1. Requisitioner checks if flag is also set in PO. 2. Requisitioner checks in PO printout if price & quantity is not visible. | V16: Priority: low
B17: P2R Indirect Business Purpose | C17: P2R | D17: SX-xxxx - to be added later | E17: Catalogue/ EPR Demands for Goods | F17: Ordering, processing, and claims | J17: As a purchaser, | K17: I do not want to create POs for suppliers / topics mentioned in the exception list | M17: so that the local procurement standard is fulfilled. | O17: n/a | V17: Invoice payment without PO. Pain point for accounting: non PO invoices; Recommendation 100% PO driven environment; clarifications needed; big ARE - multiple teams involved
B22: P2R Indirect Business Purpose | C22: P2R | D22: SX-xxxx - to be added later | E22: Catalogue/ EPR Demands for Goods | F22: Ordering, processing, and claims | J22: As a requisitioner, | K22: I want to insert the retention ID is separate field I want to be notified if defined G/L account inserted and no ID inserted field | M22: so that entire process is supported incl. invoice processing. | O22: 1. Create a PR. 2. Enter the relevant G/L account. 3. An error message appears if customer field is empty. 4. Enter the ID - no error message appears.
B23: P2R Indirect Business Purpose | C23: P2R | D23: SX-xxxx - to be added later | E23: Catalogue/ EPR Demands for Goods | F23: Ordering, processing, and claims | J23: As a requisitioner, | K23: I want to insert the Spodom ID is separate field I want to be notified if defined G/L account inserted and no ID inserted field above a threshold | M23: so that entire process is supported incl. invoice processing. | O23: 1. Create a PR. 2. Enter the relevant G/L account. 3. An error message appears if customer field is empty. 4. Enter the ID - no error message appears
B24: P2R Indirect Business Purpose | C24: P2R | D24: SX-xxxx - to be added later | E24: Catalogue/ EPR Demands for Goods | F24: Ordering, processing, and claims | L24: 1. Check Purchase Requisiton 2. Adjust Purchase Requisition and / or inquire with requester S of the verification and completion is to ensure correct content of the Purchase Requisition. The process can be in interaction between the Purchasing Center (or Local Buyer/ Commodity Manager) and the requester (ping-pong principle). Throughout central clearing the Purchase Requisition are also assigned to the suitable purchasing group for further processing. The procurement verification step is either being performed by an operational buyer from Purchasing Center, a Local Buyer or a Commodity Manager. Which purchaser is actually being involved is due to purchasing group determination. Worksplit possible (e.g.DE) GBS, CM, GBS
B25: P2R Indirect Business Purpose | C25: P2R | D25: SX-xxxx - to be added later | E25: Catalogue/ EPR Demands for Goods | F25: Ordering, processing, and claims | J25: As a purchaser, | K25: I want to add and delete line items | M25: so that the requested services and / or goods are allocated to the ESN and displayed correctly according to quotations or contracts. | O25: 1. Open PR as a purchaser and add a line item to existing PR 2. Open PR and delete one line item | V25: Priority: medium
B26: P2R Indirect Business Purpose | C26: P2R | D26: SX-xxxx - to be added later | E26: Catalogue/ EPR Demands for Goods | F26: Ordering, processing, and claims | J26: As a purchaser, | K26: I want to receive new PRs in my work overview (no notification needed) | M26: so that I can start processing the business demand. | O26: 1. PR is created. 2. Purchaser receives new PRs in their work overview. | V26: Priority: low
B27: P2R Indirect Business Purpose | C27: P2R | D27: SX-xxxx - to be added later | E27: Catalogue/ EPR Demands for Goods | F27: Ordering, processing, and claims | J27: As a purchaser, | K27: I want to receive a notification about new PRs in the system | M27: so that I shorten the throughput time. | O27: 1. PR with relevant criteria created. 2. PR assigned to puchaser. 3. Purchaser notified. | V27: Priority: low
B28: P2R Indirect Business Purpose | C28: P2R | D28: SX-xxxx - to be added later | E28: Catalogue/ EPR Demands for Goods | F28: Ordering, processing, and claims | J28: As a requisitioner, | K28: I want to get notified when my created PR got rejected incl reason | M28: so that I’m informed immediately incl. reason. | O28: 1. PR rejected from purchser 2. Requisitioner notified about rejected PR incl reason | V28: Priority: medium How to inform participants in rejected PRs?
B29: P2R Indirect Business Purpose | C29: P2R | D29: SX-xxxx - to be added later | E29: Catalogue/ EPR Demands for Goods | F29: Ordering, processing, and claims | J29: As a purchaser, | K29: I want to send back the PR to the requisitioner in case of clarification incl comment what is missing | M29: so that missing data can be filled. | O29: 1. The purchaser opens the PR. 2. Add comment and assign to requisitioner. 3. Requisitioner receives notification. 4. Requisitioner add required data and assigns back to purchaser. | V29: Priority: medium
B30: P2R Indirect Business Purpose | C30: P2R | D30: SX-xxxx - to be added later | E30: Catalogue/ EPR Demands for Goods | F30: Ordering, processing, and claims | J30: As a purchaser, | K30: I want to edit all data fields incl myMall transferred data | M30: so that the quality of the PR is ensured. | O30: 1. Purchaser opens assigned PR. 2. Purchaser check all field if editable. | V30: Priority: high
B31: P2R Indirect Business Purpose | C31: P2R | D31: SX-xxxx - to be added later | E31: Catalogue/ EPR Demands for Goods | F31: Ordering, processing, and claims | J31: As a purchaser, As a process owner, | K31: I want to receive only PRs which are relevant for me I want that PGroups are determined automatically a. Small businesses / countries: - ESN - Value - Company code - Order type b. Bigger businesses / countries: - Organizational data (department), e.g. GBS* - Location | M31: so that I can work efficiently. so that PRs can be assigned to purchasers. | O31: One of the following combinations has to be selected for verification: 1. Create PR 2. correct PGroup automatically determined according to the settings 3. Assigned purchaser(s) can see the PR in work overview | V31: Priority: medium
B32: P2R Indirect Business Purpose | C32: P2R | D32: SX-xxxx - to be added later | E32: Catalogue/ EPR Demands for Goods | F32: Ordering, processing, and claims | J32: As a business representative, As a purchaser, | K32: I want to decide about purchasing involvement I want to receive PRs in my area of responsibility | M32: so that the requested goods and / or services are verified pending on complexity level and thresholds. so that I can process efficient the PRs assigned to me. | O32: 1. Create different PRs with different data (value, ESN, organization), 2. check if additional purchaser(s) are correctly determined based on defined criteria | V32: Priority: medium
B33: P2R Indirect Business Purpose | C33: P2R | D33: SX-xxxx - to be added later | E33: Catalogue/ EPR Demands for Goods | F33: Ordering, processing, and claims | L33: 1. Expert step: Am I allowed to order? Specific commodity experts are required (e.g. hazardous materials) according to local legal requirements and internal regulations (roll-in activity). The S of the first expert verification process step is for the expert to check if it is permitted to order the required goods / services. The following activities will be performed by the expert: 1. Select PR In the work overview the expert receives the PR for review. The expert selects the PR and opens it for further processing. 2. Check PR The content of the PR is checked by the expert according to local regulations. 3. Approve PR The validation is noted via approve / reject button. On receiving the expert’s confirmation, the PR will be sent to the next process step. Communication: Expert, purchaser and requisitioner communicate offline when clarification required
B34: P2R Indirect Business Purpose | C34: P2R | D34: SX-xxxx - to be added later | E34: Catalogue/ EPR Demands for Goods | F34: Ordering, processing, and claims | J34: As an expert, | K34: I want to receive a notification of new PRs for approval in the system | M34: so that processing time is minimized. | O34: 1. Create a PR with expert approval step. 2. Expert receives notification. | V34: Priority: medium
B35: P2R Indirect Business Purpose | C35: P2R | D35: SX-xxxx - to be added later | E35: Catalogue/ EPR Demands for Goods | F35: Ordering, processing, and claims | J35: As a requisitioner, | K35: I want to be notified when a PR I created is rejected | M35: so that I can initiate a clarification process, inform the business and po-tentially create a new shopping basket. | O35: 1. PR rejected from expert 2. The requester receives a notification about rejection of the PR (push principle). | V35: Priority: medium
B36: P2R Indirect Business Purpose | C36: P2R | D36: SX-xxxx - to be added later | E36: Catalogue/ EPR Demands for Goods | F36: Ordering, processing, and claims | J36: As an expert, | K36: I only want to approve or reject PRs | M36: so that the processing time is efficient. | O36: 1. Assign PRs to a specific expert. 2. The expert cannot edit the PR, the PR can only be approved or re-jected. | V36: Priority: medium
B37: P2R Indirect Business Purpose | C37: P2R | D37: SX-xxxx - to be added later | E37: Catalogue/ EPR Demands for Goods | F37: Ordering, processing, and claims | J37: As a process owner, | K37: I want that a PR is in total rejected if one line item is rejected | M37: so that only the entire PR will be processed. | O37: 1. Create PR with multiple line items and expert approval step. 2. Expert rejects line item. 3. Entire PR is rejected. | V37: Priority: high
B38: P2R Indirect Business Purpose | C38: P2R | D38: SX-xxxx - to be added later | E38: Catalogue/ EPR Demands for Goods | F38: Ordering, processing, and claims | J38: As an expert, | K38: I want to be able to forward a work item to a specific approver | M38: so that processing time can be minimized. | O38: 1. An expert opens the PR and forward a work item to a specific ex-pert. 2. The work item is in the work overview of the new expert chosen. 3. The expert name is visible in the general workflow overview. | V38: Priority: medium
B39: P2R Indirect Business Purpose | C39: P2R | D39: SX-xxxx - to be added later | E39: Catalogue/ EPR Demands for Goods | F39: Ordering, processing, and claims | J39: As an expert, | K39: I want that that approval table entries will be adjusted regularly | M39: so that experts are determined correctly. | O39: 1. Open a ticket or address topic to a user with respective authoriza-tions. 2. Approval table is adjusted. 3. Approval restart assigns the correct approver. | V39: Priority: medium
B40: P2R Indirect Business Purpose | C40: P2R | D40: SX-xxxx - to be added later | E40: Catalogue/ EPR Demands for Goods | F40: Ordering, processing, and claims | J40: As a process owner, | K40: I want the various experts to be determined based on specific criteria | L40: Criteria: - Company code - Ordering process (free text, limit, catalog) - Accounting assignment category / type - ESN - Value from - value to - Currency - Special methods for optimized maintenance, e.g. - Evaluate special ESN / commodities - Exclude special commodities - Evaluate step in case of various G/L accounts - Additional for bigger organizations / countries: - Department (e.g. CF R) for purchasing / expert verification - Location (e.g. Mch* e.g. personal protective equipment man-ager only responsible for one location) | M40: so that each expert can check if the requisitioner is permitted to order the required goods and / or services. | O40: Create multiple PRs with above mentioned criteria to determine the ap-propriate expert and check if the correct expert was allocated in the workflow. | V40: Priority: medium
B41: P2R Indirect Business Purpose | C41: P2R | D41: SX-xxxx - to be added later | E41: Catalogue/ EPR Demands for Goods | F41: Ordering, processing, and claims | L41: The S of the PO creation process step is to finalize the PO and forward for approval. The following activities will be performed by the purchaser: 1. Create PO If a PR is created with several line items for multiple suppliers, the PR will be split into multiple POs per supplier. For PO creation we differentiate between order types: a. Catalog order The PO creation of purchase orders from preceding PR is automated. Since catalog items are pre-negotiated goods and services all relevant data for purchase order creation are known. Therefore, no purchaser interaction is necessary. b. Free text / limit order There are two options to create a PO out of PR within the limit / free text process: - The PR data is complete, and no further activities are required. The PO needs to be created automatically. - The PR data are incomplete and / or further activities are necessary. In this case the PO needs to be created manually. 2. Edit PO (valid for free text / limit order) The assigned purchaser (Operational Buyer, Regional Procurement Manager or Commodity Manager) can edit the PO. Necessary data fields, which are not covered in PR, will be completed manually in the system, e.g. - Printout media, e.g. no output flag - Goods receipt - Goods receipt reminder (roll-in activity) - Deactivation of the dunning process (roll-in activity) 3. Order PO Dependent on ordering type and procurement involvement, the PO will be ordered via system / purchaser. According to local approval regulations, the PO will be forwarded to the assigned approver and / or supplier.
B43: P2R Indirect Business Purpose | C43: P2R | D43: SX-xxxx - to be added later | E43: Catalogue/ EPR Demands for Goods | F43: Ordering, processing, and claims | J43: As a purchaser, | K43: for free text / limit PRs I want to have POs automatically created and send for approval (all mandatory data incl. fixed supplier are entered) | M43: so that the PO creation step needs no involvement of a purchaser. | O43: 1. The purchaser processes the PO (all mandatory data fields are a filled incl. fixed supplier) 2. The PO should be created automatically and sent for approval after PR is released by procurement. | V43: Priority: high
B44: P2R Indirect Business Purpose | C44: P2R | D44: SX-xxxx - to be added later | E44: Catalogue/ EPR Demands for Goods | F44: Ordering, processing, and claims | J44: As a purchaser, | K44: for free text / limit PRs I want to create the PO manually in case of using the desired supplier instead of a fixed supplier | M44: so that I can change the default output media and contact data in the PO. | O44: 1. The purchaser processes PO (all mandatory data fields are a filled and fixed supplier is not used) 2. The PO is not created automatically 3. The PO can be created manually and the output media and contact data can be edited. | V44: Priority: high
B45: P2R Indirect Business Purpose | C45: P2R | D45: SX-xxxx - to be added later | E45: Catalogue/ EPR Demands for Goods | F45: Ordering, processing, and claims | J45: As a purchaser, | K45: I want to suppress the price in the PO (either prefilled from PR or manually in PO) | M45: so that the estimated budget is not displayed in the PO printout and can-not be seen by the supplier. | O45: 1. Create PO with activated flag. 2. Open PO printout and check if price is not displayed. | V45: Priority: medium
B46: P2R Indirect Business Purpose | C46: P2R | D46: SX-xxxx - to be added later | E46: Catalogue/ EPR Demands for Goods | F46: Ordering, processing, and claims | J46: As a process owner, | K46: I want that relevant data is provided to the HANA Data Lake (GBDI) | M46: so that official Siemens PO/PVO reportings are supported. | O46: PO data is available in PO/PVO reportings. | V46: Priority: medium
B47: P2R Indirect Business Purpose | C47: P2R | D47: SX-xxxx - to be added later | E47: Catalogue/ EPR Demands for Goods | F47: Ordering, processing, and claims | J47: As a purchaser, | K47: I want to be able to change payment terms and incoterms which are pro-vided / prefilled according to supplier master data | M47: so that data deviations can be handled easily. | O47: 1. Create a PO. 2. Check if payment terms and incoterms are prefilled according to entries in supplier master data. | V47: Priority: medium
B48: P2R Indirect Business Purpose | C48: P2R | D48: SX-xxxx - to be added later | E48: Catalogue/ EPR Demands for Goods | F48: Ordering, processing, and claims | J48: As a purchaser, | K48: I want to have my contact data displayed on PO printout and EDI mes-sage based on the PGroup data (free text / limit data of purchaser should be displayed; catalog / EPR data of a central address should be possible) | M48: so that the supplier can contact purchaser in case of clarifications. | O48: Create a PO and compare the PGroup data with the address of the PO printout. | V48: Priority: medium
B49: P2R Indirect Business Purpose | C49: P2R | D49: SX-xxxx - to be added later | E49: Catalogue/ EPR Demands for Goods | F49: Ordering, processing, and claims | J49: As a process owner, | K49: I want that the invoice address is derived and displayed correctly on the PO printout and transferred in the EDI segments | M49: so that invoices coming from the supplier are addressed correctly. | O49: 1. Create PO for an EDI connected supplier. 2. Check PO printout if the invoice address is correctly displayed. 3. Check EDI message if data is in correct segments. | V49: Priority: medium
B50: P2R Indirect Business Purpose | C50: P2R | D50: SX-xxxx - to be added later | E50: Catalogue/ EPR Demands for Goods | F50: Ordering, processing, and claims | J50: As a process owner, | K50: I want that the correct invoice email address and POR email address are derived and displayed correctly on the PO printout and transferred cor-rectly in the EDI segments | M50: so that invoices from supplier will be addressed correctly (in case of email and POR are addressed to the desired email address). | O50: 1. Create a PO for an EDI connected supplier. 2. Check in the PO printout if both email addresses are correctly dis-played. 3. Check EDI message if data is in the correct segments. | V50: Priority: medium
B51: P2R Indirect Business Purpose | C51: P2R | D51: SX-xxxx - to be added later | E51: Catalogue/ EPR Demands for Goods | F51: Ordering, processing, and claims | J51: As a requisitioner, | K51: I want that the BuyerParty & BilltoParty ORG-ID is determined | M51: so that the PO contains correct data for EDI processing. | O51: Purchaser opens the PO and checks if the ORGIDs are correctly deter-mined. | V51: Priority: high
B52: P2R Indirect Business Purpose | C52: P2R | D52: SX-xxxx - to be added later | E52: Catalogue/ EPR Demands for Goods | F52: Ordering, processing, and claims | J52: As a purchaser, | K52: I want that the PO printout contains required data and a local design | M52: so that local regulations about content and guideline for design are ful-filled. | O52: Purchaser opens the PO and checks the layout and required data. | V52: Priority: high
B53: P2R Indirect Business Purpose | C53: P2R | D53: SX-xxxx - to be added later | E53: Catalogue/ EPR Demands for Goods | F53: Ordering, processing, and claims | J53: As a process owner, | K53: I want that for all countries where tax rates is required in the PO, tax rates are correct determined | M53: so that tax regulations apply. | O53: 1. Create PO for a tax relevant country. 2. Check PO, PO printout and EDI message if tax rates are correct determined. | V53: Priority: high Pain point accounting: set flag (service, goods) in PO
B54: P2R Indirect Business Purpose | C54: P2R | D54: SX-xxxx - to be added later | E54: Catalogue/ EPR Demands for Goods | F54: Ordering, processing, and claims | J54: As a process owner, | K54: I want that for all countries where withholding tax is required in the PO that withholding tax is correctly determined | M54: so that tax regulations apply. | O54: 1. Create PO for a tax relevant country. 2. Check withholding tax in PO. | V54: Priority: medium Pain point accounting: set flag (service; goods) in PO
B55: P2R Indirect Business Purpose | C55: P2R | D55: SX-xxxx - to be added later | E55: Catalogue/ EPR Demands for Goods | F55: Ordering, processing, and claims | J55: As a process owner, | K55: I want for all countries where construction withholding tax is required in the PO, building withholding tax is correctly determined | M55: so that tax regulations are apply. | O55: 1. Create PO for a tax relevant country. 2. Check if constructoin withholding tax is correctly determined in the PO. | V55: Priority: medium
B56: P2R Indirect Business Purpose | C56: P2R | D56: SX-xxxx - to be added later | E56: Catalogue/ EPR Demands for Goods | F56: Ordering, processing, and claims | J56: As a process owner, | K56: I want for all countries where VAT ID is required in the PO that the VAT ID is correctly determined | M56: so that tax regulations apply. | V56: Priority: medium
B57: P2R Indirect Business Purpose | C57: P2R | D57: SX-xxxx - to be added later | E57: Catalogue/ EPR Demands for Goods | F57: Ordering, processing, and claims | J57: As a requisitioner, | K57: I want to get displayed supplier with R4B status only | M57: so that unqualified supplier cannot be chosen. | O57: 1.Create a PR. 2. Try to choose an unqualified supplier 3. Supplier should not be displayed | V57: Incl. also in direct sourcing workstream.
B58: P2R Indirect Business Purpose | C58: P2R | D58: SX-xxxx - to be added later | E58: Catalogue/ EPR Demands for Goods | F58: Ordering, processing, and claims | J58: As a process owner, | K58: I want that invoices for trusted partner are paid without GR / performance receipt booking | M58: so that a lean processing time can be ensured. | O58: 1. Create a PO with a trusted partner. 2. Create an invoice without deviations. 3. Invoice is paid without GR / performance receipt booking. | V58: Two-way-match (price, quantity) applies.
B59: P2R Indirect Business Purpose | C59: P2R | D59: SX-xxxx - to be added later | E59: Catalogue/ EPR Demands for Goods | F59: Ordering, processing, and claims | J59: As a requisitioner, | K59: I want to get an overview of the suppliers delivery performance and an alerting, if known delivery problems were reported for this supplier | M59: so that I can choose another supplier if the delivery performance is too low for my needs | O59: 1. Create a PR/ PO 2. Get the supplier delivery performance | V59: Incl. also in direct sourcing workstream.
B60: P2R Indirect Business Purpose | C60: P2R | D60: SX-xxxx - to be added later | E60: Catalogue/ EPR Demands for Goods | F60: Ordering, processing, and claims | L60: 2. Expert step: Correct processing of PO? The determination of the required experts happens automatically based on defined conditions. The following experts could be involved in the purchase order completion step: • Financial Expert: The Financial Expert will have to validate, complete and confirm the accounting data of the purchase order. • Asset Manager: If the purchase order contains asset related items, the asset manager will be involved for completion. The asset manager needs to access the purchase order and verify and change the asset related data in the line item accounting data. • ECC Officer: In case the purchase order contains items which are ECC relevant • Tax: Potential involvement in expert verification
B61: P2R Indirect Business Purpose | C61: P2R | D61: SX-xxxx - to be added later | E61: Catalogue/ EPR Demands for Goods | F61: Ordering, processing, and claims | J61: As a process owner, | K61: I want that the entire PO is rejected when a line item gets rejected | M61: so that only the entire PO can be processed. | O61: 1. Open the PO in a work overview. 2. Reject one line item. 3. Either no possibility to reject one line item or rejection of line item leads to the rejection of entire PO. | V61: Priority: high
B62: P2R Indirect Business Purpose | C62: P2R | D62: SX-xxxx - to be added later | E62: Catalogue/ EPR Demands for Goods | F62: Ordering, processing, and claims | J62: As a PO expert, | K62: I want to receive a push notification when new POs for approval arise | M62: so that I do not have to check proactively the system for new POs. | O62: 1. Create PO where an expert approval is required. 2. Check if PO expert receives a push notification for PO approval. | V62: Priority: high
B63: P2R Indirect Business Purpose | C63: P2R | D63: SX-xxxx - to be added later | E63: Catalogue/ EPR Demands for Goods | F63: Ordering, processing, and claims | J63: As a PR requisitioner, | K63: I want to get informed and notified about the reason if a PO is rejected | M63: so that I do not have to check proactively in the system the status of POs. | O63: 1. Create PO where an expert approval is required. 2. The expert rejects the PO. 3. Check if the PR requisitioner receives a push notification. | V63: Priority: medium
B64: P2R Indirect Business Purpose | C64: P2R | D64: SX-xxxx - to be added later | E64: Catalogue/ EPR Demands for Goods | F64: Ordering, processing, and claims | J64: As a process owner, | K64: I want that PO experts are determined based on following criteria 1. Company Code 2. ESN 3. Value 4. Accounting data 5. Supplier master data 6. Cross border business (country of delivery address, country of sup-plier, country of requisitioner) | M64: so that the experts can verify the PO and if necessary, edit relevant fields (e.g. account assignment, accounting element ...). | O64: Create a PO with relevant data for expert determination. 2. Check if the PO expert is correct determined. | V64: Priority: medium
B65: P2R Indirect Business Purpose | C65: P2R | D65: SX-xxxx - to be added later | E65: Catalogue/ EPR Demands for Goods | F65: Ordering, processing, and claims | J65: As a PO expert, | K65: I want to edit relevant data fields in the PO, if required (e.g. asset accounting expert wants to change accounting data) | M65: so that I can send the PO for approval and further processing is ensured. | O65: 1. Open the PO in the expert work overview. 2. Check if relevant data fields are editable. 3. Approve the PO. | V65: Priority: low
B66: P2R Indirect Business Purpose | C66: P2R | D66: SX-xxxx - to be added later | E66: Catalogue/ EPR Demands for Goods | F66: Ordering, processing, and claims | J66: As an asset expert, | K66: I want to be involved in the PO expert verification step in case of - usage of the asset accounting type - or when the price per unit for goods is above a defined threshold | M66: so that the correctness of the asset process is ensured. | O66: 1. Create a PO with asset accounting type. 2. Asset expert involved in expert verification step. 1. Create a PO for goods with unit price above defined threshold. 2. Asset expert involved in expert verification step.G57 | V66: Process not finally defined yet (resp. Christina Freudiger)
B67: P2R Indirect Business Purpose | C67: P2R | D67: SX-xxxx - to be added later | E67: Catalogue/ EPR Demands for Goods | F67: Ordering, processing, and claims | J67: As an asset expert, | K67: I want to be able to edit accounting elements and asset master data | M67: so that the correctness of the asset process is ensured. | O67: 1. Create a PO with asset accounting type. 2. Asset expert involved in expert verification step. 3. Asset expert can edit the PO. 1. Create a PO for goods with unit price above defined threshold. 2. Asset expert involved in expert verification step. 3. Asset expert can edit the PO. | V67: Process not finally defined yet (resp. Christina Freudiger)
B68: P2R Indirect Business Purpose | C68: P2R | D68: SX-xxxx - to be added later | E68: Catalogue/ EPR Demands for Goods | F68: Ordering, processing, and claims | L68: The S of the LoA approval process step is to approve the PO according to the signature circular stipulations. [Circular “Granting and exercise of signature authorizations”, No. 1_C_109, Version 2.4] The following chapter is based on the existing signature circular and local regulations. A revision of the circular is planned for 2022 within the SHERPA program (BPH strategic procurement). With a signature, the approver confirms the correctness of a PO regarding financial, tax related and, both internal and external legal requirements. The LoA approver determination is configured according to certain rules: - Applicable approval levels are identified, e.g. based on total value, item value, etc. - The corresponding approver is assigned, e.g. based on accounting data. The approval task is based on the line item. Approval is dependent on the valid signature authorization mandate. For the LoA approval part there could be up to two approval steps determined depending on PO value based on signature circular. Above 5.000EUR two approvals are mandatory. One of the approvers must be a commercial approver. In general there is functional and commercial approver involved. For high value POs some units involve additional approvers In general, S/4 should allocate approvers based on accounting elements. External data sources, comparable to the existing SAMIS tool, should be taken into consideration for future usage (roll-in activity). Approval An approver should be able to approve POs without logging into the S/4 system. The following solutions should be provided: - Fiori app - Unified Worklist (UWL) mobile phone app already exists for Germany - Email with approval functionality or similar solution The following activities will be performed by the approver: 1. Select PO The approver should be notified about newly created POs for approval. The notification, e.g. via email, should contain a link to open and review the PO and attached documents in Fiori app. Within the work overview in S/4 Fiori, Fiori app or UWL, the approver should receive the PO for approval. The manager selects the purchase order and opens it for further processing. 2. Check PO The approver checks the details in the PO. 3. Approve PO The approver approves or rejects the allocated PO, a change option is not permitted for their role. In case of PO rejection, - the approver should state reasons for their decision. A comment should be added into the notification field. - line items are not considered as independent. If one line item should be rejected in the PO, the entire PO including all line items should be rejected. The purchaser can still make changes to the PO when, e.g., a reason for rejection is provided by a manager. In case of PO approval, - the next level of approval should be determined by the system, depending on local requirements. - and no further approvals are required, the PO is finally approved and should be sent to the supplier, unless stated otherwise in the PO. Adaption of delivery date - Situation: In some cases, the processing lead time and approval of the PR / PO takes longer than usual. - Challenge: A delivery date in the past should be avoided. - Solution: The delivery date should be adapted automatically after final approval. Determination of approver Approver determination can be configured via certain rules. - In a first step applicable approval levels need to be identified, e.g. based on accounting data, total value, item value etc. (roll-in activity). - The approval work item should be based on line item level. - A potential risk has to be considered: - Situation: For a few businesses, e.g. SRE and some WBS elements of SMO, the automated determination of approvers is not possible. - Challenge: Determine the correct approver. - Solution: Replace “dummy approver” with an existing approver (non standard functionality). Execution of approval - Situation: The validation of the individual signature mandate during approval is not foreseen. - Challenge: The system should not validate whether the approver / substitute (still) has the necessary authorization to perform the action. In case the approver is not authorized (anymore), no error message should inform them to redirect the process to a different authorized approver out from the work list, nor to inform the system support. - Solution: The principle of ownership culture applies. The approver should be aware if they are authorized and the right addressee to perform the particular approval.
B69: P2R Indirect Business Purpose | C69: P2R | D69: SX-xxxx - to be added later | E69: Catalogue/ EPR Demands for Goods | F69: Ordering, processing, and claims | J69: As a process owner, | K69: I want that approvers are determined based on the signature circular and local regulation based on 1. SAP System 2. Company Code 3. Document type (freetext / catalog and easy price request / limit) 4. Internal / External orders 5. Value (from, to), currency based on “business transaction tables”) or level of authority 6. Accounting type 7. Accounting element: for WBS, order, asset, etc. the “responsible cost center” of accounting element should be used 8. Role (functional or commercial approver) 9. “Substitution flag” (to identify the correct approver if more than one approver has the identical authorization for the same cost center) 10. Databases for signature authorizations (e.g. SAMIS, SIGN) can be used for prefilling of approval tables. If no database is exists, a manual maintenance option should be offered. 11. An efficient method for maintenance should be considered | M69: so that approval is according to the Siemens guideline. | O69: 3. Create multiple POs with different values and account assignment categories. 4. Check if the correct amount of approval steps is determined. 5. Check if the correct approvers are determined. | V69: Priority: high
B70: P2R Indirect Business Purpose | C70: P2R | D70: SX-xxxx - to be added later | E70: Catalogue/ EPR Demands for Goods | F70: Ordering, processing, and claims | J70: As a LoA approver, | K70: I want to approve via smartphone, tablet or computer and all necessary data for decision are provided | M70: so that I can minimize the processing time. | O70: 1. Create multiple POs. 2. Check the opportunity for approval for tablet, computer and smartphone. 3. All relevant data are correctly displayed for decision. 4. Check if the POs can be approved and rejected via smartphone, tablet or computer. | V70: Priority: medium
B71: P2R Indirect Business Purpose | C71: P2R | D71: SX-xxxx - to be added later | E71: Catalogue/ EPR Demands for Goods | F71: Ordering, processing, and claims | J71: As a process owner, | K71: I want that approvers are determined on item level based on total value of PO and a PO approval is given when all line items are approved | M71: so that approvers only be responsible for their dedicated line items. | O71: 1. Create multiple POs with different cost center with a higher value (total value of PO would determine a different approver than line item value). 2. Check if the approvers are determined based on total PO value. 3. Check if the PO is not approved if not all approvals are executed. 4. Check if the PO is approved if all approvals are executed. | V71: Priority: medium
B72: P2R Indirect Business Purpose | C72: P2R | D72: SX-xxxx - to be added later | E72: Catalogue/ EPR Demands for Goods | F72: Ordering, processing, and claims | J72: As a process owner, | K72: I want that the entire PO is rejected if an approver rejects the PO | M72: so that a PO is processed as a whole. | O72: 1. Create a PO with multiple approvers. 2. One approver rejects the PO. 3. Check if the PO has status “rejected”. 4. Check if work items from other approvers disappears. | V72: Priority: medium
B73: P2R Indirect Business Purpose | C73: P2R | D73: SX-xxxx - to be added later | E73: Catalogue/ EPR Demands for Goods | F73: Ordering, processing, and claims | J73: As a purchaser, | K73: I want to edit rejected Pos | M73: so that I can avoid creating a new PO. | O73: 1. Create a PO. 2. Reject a PO. 3. The purchaser opens a rejected PO and edits the PO. 4. The PO is sent for approval (again). | V73: Priority: medium
B74: P2R Indirect Business Purpose | C74: P2R | D74: SX-xxxx - to be added later | E74: Catalogue/ EPR Demands for Goods | F74: Ordering, processing, and claims | J74: As a process owner, | K74: I want that work items which cannot be approved by the selected ap-prover (no substitute maintained) should be manually forwarded to a substitute | M74: so that processing time is minimized. | O74: 1. Create a PO. 2. User with the respective authorizations can forward the PO work item. 3. Check if new assigned approver can see and approve / reject the PO. | V74: Priority: high
B75: P2R Indirect Business Purpose | C75: P2R | D75: SX-xxxx - to be added later | E75: Catalogue/ EPR Demands for Goods | F75: Ordering, processing, and claims | J75: As a LoA approver, | K75: I want to receive a push notification if a new PO is assigned to me for approval | M75: so that processing time can be minimized. | O75: 1. Create a PO with LoA approval step. 2. Check if a LoA approver received a push notification. | V75: Priority: medium
B76: P2R Indirect Business Purpose | C76: P2R | D76: SX-xxxx - to be added later | E76: Catalogue/ EPR Demands for Goods | F76: Ordering, processing, and claims | J76: As a requisitioner, | K76: I want to receive a push notification with a comment if the respective PO of my PR is rejected | M76: so that process time is minimized. | O76: 1. Create a PO. 2. Reject a PO with reason for rejection (reason is mandatory). 3. Check if requisitioner receives a notification incl. reason for rejection. | V76: Priority: medium
B77: P2R Indirect Business Purpose | C77: P2R | D77: SX-xxxx - to be added later | E77: Catalogue/ EPR Demands for Goods | F77: Ordering, processing, and claims | J77: As a process owner, | K77: I want in case of cost splitting within a line item, (approver per cost center) that all involved approvers have to approve the PO | M77: so that all budget responsible have signed. | O77: 1. Create a PO with several cost centers so that multiple LoA approver are required. 2. Check if all approvers are determined. 3. Check if all approvers have a work item in their work overview. 4. All approvers need to approve. 5. Check if approval step has the status “approved" | V77: Priority: medium
B78: P2R Indirect Business Purpose | C78: P2R | D78: SX-xxxx - to be added later | E78: Catalogue/ EPR Demands for Goods | F78: Ordering, processing, and claims | J78: As a LoA approver, | K78: I want to approve all line items in a PO (which are assigned to me) with one click | L78: Use case 1: A PO with different accounting types, one cost center line item 1 - asset - cost center 1 and line item 2 - cost center - cost center 1 Use case 2: different cost centers, one approver line item 1 - cost center 1 - approver 1 and line item 2 - cost center 2 - approver 1 | M78: so that processing time in minimized | O78: 1. Create a PO with the following data Use case 1: A PO with different accounting types, one cost center line item 1 - asset - cost center 1 and line item 2 - cost center - cost center 1 Use case 2: different cost centers same approver line item 1 - cost center 1 - approver 1 and line item 2 - cost center 2 - approver 1 2. Check if the approver is correctly assigned. 3. Check if the approver can approve all item with one click. | V78: Priority: medium
B79: P2R Indirect Business Purpose | C79: P2R | D79: SX-xxxx - to be added later | E79: Catalogue/ EPR Demands for Goods | F79: Ordering, processing, and claims | J79: As a process owner, | K79: I want that only approvers with an activated user account approve Pos | M79: so that the identity of user was verified. | O79: 1. Create a PO where an approver without active user account has to approve. 2. Check if the approver cannot access and approve. | V79: Priority: medium
B80: P2R Indirect Business Purpose | C80: P2R | D80: SX-xxxx - to be added later | E80: Catalogue/ EPR Demands for Goods | F80: Ordering, processing, and claims | J80: As a process owner, | K80: I want that the next level of approver applies in case of no determination of an approver in a lower range of value I want that the workflow responsible gets notified In case no approver is determined, | M80: so that processing time for approvals can be minimized. | O80: 1. Create a PO where the value range is not maintained. 2. Check if the next approval level applies. 3. Create a PO where no approver is maintained (e.g. new cost cen-ters) 4. Check if the workflow responsible gets notified. | V80: Priority: medium
B81: P2R Indirect Business Purpose | C81: P2R | D81: SX-xxxx - to be added later | E81: Catalogue/ EPR Demands for Goods | F81: Ordering, processing, and claims | J81: As a purchaser, | K81: I want edit POs which are currently in the approval step | M81: so that I can correct errors without restarting the process. | O81: 1. Create a PO and start the approval step. 2. The purchaser calls and edits the PO. 3. During the “PO edit mode” the work item for approval should dis-appear in the approval step. 4. After editing the PO, the PO is again in the approval step. | V81: Priority: medium
B82: P2R Indirect Business Purpose | C82: P2R | D82: SX-xxxx - to be added later | E82: Catalogue/ EPR Demands for Goods | F82: Ordering, processing, and claims | J82: As a purchaser, | K82: I want to get the delivery date updated if the delivery date is in the past after final approval | M82: so that supplier receives the correct delivery date. | O82: 1. Create a PO. 2. Approve the PO after the delivery date is exceeded Use case 1: Approval date + supplier standard delivery time is lower or equal to delivery date in PO  no adaption of delivery date necessary Use case 2: Approval date + supplier standard delivery time > de-livery date in PO  adaption of delivery date to approval date + supplier standard delivery time 3. Check if the delivery date is updated | V82: Priority: medium
B83: P2R Indirect Business Purpose | C83: P2R | D83: SX-xxxx - to be added later | E83: Catalogue/ EPR Demands for Goods | F83: Ordering, processing, and claims | J83: As a process owner, | K83: I want that approval data is prefilled out of the signature databases | M83: so that additional maintenance effort is avoided. | O83: 1. Signature database data is available in S/4. 2. Changes in signature database are displayed in S/4 (update frequency tbc) | V83: Priority: medium
B84: P2R Indirect Business Purpose | C84: P2R | D84: SX-xxxx - to be added later | E84: Catalogue/ EPR Demands for Goods | F84: Ordering, processing, and claims | J84: As a requisitioner and LoA approver, | K84: we want get notified on a regular basis, if a PO is not approved in a specific time frame | M84: so that processing time can be minimized. | O84: 1. Create a PO with status “in approval”. 2. Wait until the time frame set is overdue (x days). 3. Check if a LoA approver receivs a reminder notification. | V84: Priority: medium
B85: P2R Indirect Business Purpose | C85: P2R | D85: SX-xxxx - to be added later | E85: Catalogue/ EPR Demands for Goods | F85: Ordering, processing, and claims | J85: As a requisitioner, purchaser and approver, | K85: we want to be able to add “adhoc” approvers manually in the approval pro-cess, | M85: so that approvers required can be involved. | O85: 1. Valid maybe also for PR 2. Challenge how could a requisitioner do this? 3. Only user with respective authorizations should available as adhoc approvers
B86: P2R Indirect Business Purpose | C86: P2R | D86: SX-xxxx - to be added later | E86: Catalogue/ EPR Demands for Goods | F86: Ordering, processing, and claims | J86: As a requisitioner, purchaser and approver, | K86: we want to be able to replace approvers manually in approval process, according to LoA authorizations a) If no approvers could be determined a fallback or dummy ap-prover should be chosen b) Existing approver is currently not available | M86: so that approval process can be fastened. | O86: 1. Search for a PO. 2. Open the PO and replace the existing approver. | V86: 1. In search result only approvers with same or higher LoA should be displayed 2. Challenge how could a requisitioner do this?
B87: P2R Indirect Business Purpose | C87: P2R | D87: SX-xxxx - to be added later | E87: Catalogue/ EPR Demands for Goods | F87: Ordering, processing, and claims | J87: As a process owner, | K87: I want to ensure that same LoA approver cannot perform two approvals for one PO | M87: so that the approval is according to regulations. | O87: 1. Create PO with two LoA approval steps. 2. Determine one approver for two approval steps. 3. An error message appears.
B88: P2R Indirect Business Purpose | C88: P2R | D88: SX-xxxx - to be added later | E88: Catalogue/ EPR Demands for Goods | F88: Ordering, processing, and claims | L88: The S of the PO release process step is to prepare the final approved PO for transfer to the supplier. If there is no approval needed, the PO will be released automatically. The usage of the correct PO printout format is based on local legal requirements and internal regulations (roll-in activity). [Siemens Stationery “Corporate Design Guidelines”, Status December_2020 (S. 49)] Archiving A PDF copy of the PO printout after PO release should be stored as an attachment in S/4 for legal purposes.
B89: P2R Indirect Business Purpose | C89: P2R | D89: SX-xxxx - to be added later | E89: Catalogue/ EPR Demands for Goods | F89: Ordering, processing, and claims | J89: As a purchaser, | K89: I want that the language of the PO printout corresponds to the language of supplier master data | M89: so that miscommunication towards the supplier can be avoided. | O89: 1. Create POs for several suppliers with different languages. 2. Check if the PO printout language is the correct supplier language. | V89: Priority: medium
B90: P2R Indirect Business Purpose | C90: P2R | D90: SX-xxxx - to be added later | E90: Catalogue/ EPR Demands for Goods | F90: Ordering, processing, and claims | J90: As a purchaser, | K90: I want to have copy of the PO printout as soon as it is created | M90: so that a copy of for legal purposes is stored in the system. | O90: 1. Create a PO. 2. Check if a copy of the PO printout is stored as attachment in the system. 3. Create a supplier relevant PO change. 4. Check if the PO change is stored as attachment in the system. | V90: Priority: medium
B91: P2R Indirect Business Purpose | C91: P2R | D91: SX-xxxx - to be added later | E91: Catalogue/ EPR Demands for Goods | F91: Ordering, processing, and claims | J91: As a purchaser, | K91: I want to rename the PO printout from “Order” to “Order Change” in case adjustments in the PO are required, | M91: so that miscommunication towards the supplier can be avoided. | O91: 1. Create PO 2. Change in PO supplier relevant data 3. Check printout if “Order Change” is visible 4. Check printout if all line items are visible | V91: Priority: medium
B92: P2R Indirect Business Purpose | C92: P2R | D92: SX-xxxx - to be added later | E92: Catalogue/ EPR Demands for Goods | F92: Ordering, processing, and claims | J92: As a purchaser, | K92: I want that PO printout form is adjusted per country | M92: so that Siemens guidelines and local regulations are fulfilled. | O92: 1. Create PO for different legal entities and languages 2. Check if content is correctly displayed | V92: Priority: medium
B93: P2R Indirect Business Purpose | C93: P2R | D93: SX-xxxx - to be added later | E93: Catalogue/ EPR Demands for Goods | F93: Ordering, processing, and claims | L93: The S of the supplier communication process step is to ensure the correct transfer of the PO to the supplier. The supplier communication data in the PO is automatically prefilled from the supplier master data. This data can be changed manually during the PO creation process by the purchaser, e.g. replacing the prefilled email address or switching the output media from fax to email.
B94: P2R Indirect Business Purpose | C94: P2R | D94: SX-xxxx - to be added later | E94: Catalogue/ EPR Demands for Goods | F94: Ordering, processing, and claims | J94: As a purchaser, | K94: I want that PO is transferred according to the output media setting in the PO (prefilled from supplier master data, editable for purchaser) | M94: so that the PO is transferred as agreed with the supplier. | O94: 1. Create several POs with different output media settings - EDI (Classic EDI, SupplyON, or other future platforms) - Email - Fax (roll-In activity) - No output, if transfer is suppressed by the purchaser 2. Check if the PO transfer to the supplier worked correctly. | V94: Priority: medium
B95: P2R Indirect Business Purpose | C95: P2R | D95: SX-xxxx - to be added later | E95: Catalogue/ EPR Demands for Goods | F95: Ordering, processing, and claims | J95: As a purchaser, | K95: I want to decide if a PO change should be sent to supplier | M95: so that the supplier receives only a “PO Change” document if changed data fields are relevant for them. | O95: 1. Create a PO. 2. Change the PO. 3. Mark the PO “to be sent to the supplier” 4. Check if the PO is sent to the supplier 5. Mark the PO “not be sent to supplier” 6. Check if the PO is not sent to supplier | V95: Priority: medium
B96: P2R Indirect Business Purpose | C96: P2R | D96: SX-xxxx - to be added later | E96: Catalogue/ EPR Demands for Goods | F96: Ordering, processing, and claims | J96: As a purchaser, | K96: I want to be able to decide if automatically initiated PO changes based on PORs (price reduction or change of delivery date) should be sent to sup-plier | M96: so that misunderstandings with the supplier for Siemens internal data changes can be avoided. | O96: 1. Create the PO. 2. Create the POR with deviations so that a purchaser is involved. 3. Check if the purchaser can mark / decide if the PO should be sent to the supplier or not. | V96: Priority: medium
B97: P2R Indirect Business Purpose | C97: P2R | D97: SX-xxxx - to be added later | E97: Catalogue/ EPR Demands for Goods | F97: Ordering, processing, and claims | J97: As a purchaser, | K97: I want that attachments in the PO marked as “external” should be sent to supplier (email, EDI) | M97: so that the supplier receives all relevant information. | O97: 1. Create a PO incl. attachments. Mark the PO as “external” for email transfer. 2. Create a PO incl. attachment. Mark the PO as “external” for EDI transfer. 3. Check the email sent to the supplier if attachments are included. 4. Check the EDI message to the supplier if attachments are included. | V97: Priority: medium
B98: P2R Indirect Business Purpose | C98: P2R | D98: SX-xxxx - to be added later | E98: Catalogue/ EPR Demands for Goods | F98: Ordering, processing, and claims | J98: As a purchaser, | K98: I want to decide (manually) if a PO should be sent to supplier (invoice already received from the supplier) | M98: so that POs for internal purposes are not sent to the supplier. | O98: 1. Create a PO. 2. Mark the PO „not to be sent“. 3. Check if the PO is not sent to the supplier. | V98: Priority: medium
B99: P2R Indirect Business Purpose | C99: P2R | D99: SX-xxxx - to be added later | E99: Catalogue/ EPR Demands for Goods | F99: Ordering, processing, and claims | J99: As a process owner, | K99: I want to automatically notify the supplier about outstanding delivery in (already expected GR, delivery date exceeded, GR not booked (line item related)) | M99: so that manual effort is reduced. | O99: 1. Create PO with “GR expected” and dunning process activated 2. Wait until delivery date exceeded 3. Check if notification / reminder about outstanding delivery for rel-evant items was sent out | V99: Priority: medium
B100: P2R Indirect Business Purpose | C100: P2R | D100: SX-xxxx - to be added later | E100: Catalogue/ EPR Demands for Goods | F100: Ordering, processing, and claims | J100: As a requisitioner, | K100: I want to have my contact data displayed in the PO printout and EDI | L100: as technical contact in case of inquiry of supplier | M100: so that clarifications can be processed faster. | O100: 1. Create a PO. 2. Open a PO printout and check if technical contact is correctly dis-played. 3. Create a PO with EDI. 4. Open the EDI message and check if technical contact is correctly dis-played.
B101: P2R Indirect Business Purpose | C101: P2R | D101: SX-xxxx - to be added later | E101: Catalogue/ EPR Demands for Goods | F101: Ordering, processing, and claims | L101: The purpose of the POR process step is to ensure that the POR received from the supplier confirms the PO. A supplier has to reply to the purchase order and confirm whether the ordered quantity of goods or services can be delivered at the time and for the price requested, as well as that the Siemens terms and conditions apply. To identify possible deviations, the received POR will be matched with the corresponding PO. SHERPA workstream logistics will decide on future processing and the technical solution for this step. In general, an SAP internal realization is favored including using EDI. Input media A POR can either be received by fax, post, email or EDI. 1. PORs received by fax or post will be compared with the PO and processed manually by the purchaser. 2. PORs received via email (PDF) should be automatically read by a scanning service. The POR should be transferred automatically via EDI and follows the EDI process. 3. PORs received via email (pdf), which cannot be automatically read by a scanning service, should be sent via email to the allocated purchaser. The purchaser manually compares the POR and PO, and takes care of changes in the PO, if required. 4. PORs received via EDI, an automatic POR and PO comparison check should be conducted. EDI The following three use cases for EDI PORs applies: 1. Use case 1: Deviations beyond defined tolerances If deviations beyond the defined tolerances are identified within the system, the POR has to be send automatically to the respective purchaser with an overview of the deviations. a. Received POR The POR received via EDI. b. Compares PO and POR The system compared the POR and the corresponding PO. Deviations beyond the defined tolerances (roll-in activity) are identified. c. Assign PO The POR will be routed to the work overview of the responsible purchaser. The purchaser opens work item. d. Review deviation Purchaser manually reviews the deviations. e. Accept / reject POR Purchaser rejects or accepts deviation after clarification. f. Edit PO If deviations are accepted, the PO has to be edited and if necessary, the PO change should be resent to the supplier. 2. Use case 2: Deviations within tolerances a. Receive POR The POR received via EDI. b. System compares PO and POR The system compared the POR and the corresponding PO. Deviations within the defined tolerances (roll-in activity) are identified. c. Edit and document PO The received POR needs to be documented automatically in the PO. The PDF should be attached, and the reference number deposited under “order acknowledgement” and PO must be adjusted. d. Inform supplier about PO change (optional) Depending on criteria, the PO change needs to be sent automatically to the supplier according to the initial PO. 3. Use case 3: No deviations a. System compares PO and POR The system compared the POR and the corresponding PO. b. Document PO The received POR needs to be documented automatically in the PO. The PDF should be attached, and the reference number deposited under “order acknowledgement”. Outstanding PORs (roll-in activity) Automatic monitoring of outstanding POR line items via a scheduled system job scanning is required. based on the criteria (POR expected and GR not posted or invoice received) purchasing organization and suppliers (optional). According to pre-defined criteria, affected purchase orders should be identified and a notification should be sent to the supplier, to the purchaser and / or the requisitioner. Therefore, several levels and reminder notifications should be defined, e.g., x days after purchase order release.
B102: P2R Indirect Business Purpose | C102: P2R | D102: SX-xxxx - to be added later | E102: Catalogue/ EPR Demands for Goods | F102: Ordering, processing, and claims | J102: As a purchaser, | K102: I want to receive PORs with deviations beyond tolerances in my work overview. These are automatically identified by the system by comparing EDI POR with the PO | M102: so that deviations can be clarified, and the purchaser can accept or reject the POR. | O102: 1. Create a PO. 2. Create a POR with deviation beyond tolerances. 3. Check if the POR appears in the purchaser’s work overview and if deviations are displayed correctly. 4. The purchaser accepts the POR and has the possibility to decide if a PO change should be sent to supplier. 5. After acceptance the POR is maintained in PO. 6. The PO date fields are updated with the POR data. | V102: Priority: medium
B103: P2R Indirect Business Purpose | C103: P2R | D103: SX-xxxx - to be added later | E103: Catalogue/ EPR Demands for Goods | F103: Ordering, processing, and claims | J103: As a purchaser, | K103: I want to receive PORs with deviations within tolerances in my work overview. These are automatically identified by the system by comparing EDI POR with the PO | M103: so that deviations can be clarified, and the purchaser can accept or reject the POR. | O103: 1. Create a PO. 2. Create a POs with different deviations within tolerances. 3. Check if the POR is automatically maintained in the PO. 4. Check if the PO data field are updated with the respective POR data. 5. Check if the deviations are predefined to be sent to supplier, and of the PO change is sent to supplier. 6. Check if the deviations are predefined NOT to be sent to supplier, and the PO change is NOT sent to the supplier. | V103: Priority: medium
B104: P2R Indirect Business Purpose | C104: P2R | D104: SX-xxxx - to be added later | E104: Catalogue/ EPR Demands for Goods | F104: Ordering, processing, and claims | J104: As a purchaser, | K104: I want that PORs without deviation are documented in the dedicated field in the PO | M104: so that I can see the status “POR sent”. | O104: 1. Create a PO. 2. Create a POR without price deviations. 3. Check if the POR is documented in the dedicated field. 4. Check if the PO change is NOT sent to the supplier. | V104: Priority: medium
B105: P2R Indirect Business Purpose | C105: P2R | D105: SX-xxxx - to be added later | E105: Catalogue/ EPR Demands for Goods | F105: Ordering, processing, and claims | J105: As a process owner, | K105: I want to define tolerances (lower value and higher value) for dedicated data fields (e.g. price, delivery date) | M105: so that manual effort is avoided. | O105: Check if tolerances can be maintained from an administrator. | V105: Priority: medium
...

Sheet P2P_Experts
A1: Story # | B1: Workstream | C1: Team | D1: Polarion # | E1: Scenario | F1: Level 1 | G1: Level 2 | H1: Level 3 | I1: Level 4 | J1: I as a (persona/ WHO) | K1: want to… (WHAT) | L1: Detailed Description | M1: so that… (WHY) | N1: using application/3rd Party Tools/interface (HOW) | O1: Acceptance Criteria | P1: Value Flow Items | Q1: Master Data Items | R1: SAP Best Practice | S1: SAP Module - Core | T1: SAP Module - Public Cloud | U1: Functional Shift | V1: Notes
B2: P2R Indirect Business Purpose | C2: P2R | D2: SX-xxxx - to be added later | E2: Catalogue/ EPR Demands for Goods | F2: Ordering, processing, and claims | J2: As a process owner, | K2: I want the various experts to be determined based on specific criteria | L2: Criteria: - Company code - Ordering process (free text, limit, catalog) - Accounting assignment category / type - ESN - Value from - value to - Currency - Special methods for optimized maintenance, e.g. - Evaluate special ESN / commodities - Exclude special commodities - Evaluate step in case of various G/L accounts - Additional for bigger organizations / countries: - Department (e.g. CF R) for purchasing / expert verification - Location (e.g. Mch* e.g. personal protective equipment man-ager only responsible for one location) | M2: so that each expert can check if the requisitioner is permitted to order the required goods and / or services. | O2: Create multiple PRs with above mentioned criteria to determine the ap-propriate expert and check if the correct expert was allocated in the workflow. | V2: Priority: medium
B3: P2R Indirect Business Purpose | C3: P2R | D3: SX-xxxx - to be added later | E3: Catalogue/ EPR Demands for Goods | F3: Ordering, processing, and claims | J3: As a requisitioner, | K3: 1. I want to have a separate field where I can enter the ID 2. I want that entered ID is confirmed from SATO tool 3. I want to be able to search for an ID 4. I want to be notified if defined G/L account inserted and no ID inserted field 5. I want to create an ID from PR in SATO tool | M3: so that entire process is supported incl. invoice processing | O3: 1. Create a PR. 2. Enter the relevant G/L account. 3. An error message appears if customer field is empty. 4. Enter a wrong ID. 5. An error message appears. 6. Enter the correct ID. 7. No error message appears. 8. Open search help and search for an ID in SATO tool via PR. 9. Create a new PR. 10. Open search field and push button create ID, fill in a form data, send data to SATO tool and receive a new created ID.
B4: P2R Indirect Business Purpose | C4: P2R | D4: SX-xxxx - to be added later | E4: Catalogue/ EPR Demands for Goods | F4: Ordering, processing, and claims | J4: As a requisitioner, | K4: I want to insert the Spodom ID is separate field I want to be notified if defined G/L account inserted and no ID inserted field above a threshold | M4: so that entire process is supported incl. invoice processing. | O4: 1. Create a PR. 2. Enter the relevant G/L account. 3. An error message appears if customer field is empty. 4. Enter the ID - no error message appears
B5: P2R Indirect Business Purpose | C5: P2R | D5: SX-xxxx - to be added later | E5: Catalogue/ EPR Demands for Goods | F5: Ordering, processing, and claims | J5: As a process owner, | K5: I want to receive the foreign trade data for catalog items from myMall | M5: so that intrastat reporting can be supported for catalog items or other cross border topics | O5: Create catalog myMall SC with foreign trade relevant criteriaCheck if for-eign trade data are transferred

Sheet Temp_Supplier_Integration
S1: Comments
A2: Story # | B2: Workstream | C2: Sub Process | D2: Polarion # | E2: Process Step | F2: I as a (persona/ WHO) | G2: want to… (WHAT) | H2: Detailed Description | I2: so that… (WHY) | J2: using application/3rd Party Tools/interface (HOW) | K2: Acceptance Criteria | L2: Value Flow Items | M2: Master Data Items | N2: SAP Best Practice | O2: SAP Module - Core | P2: SAP Module - Public Cloud | Q2: Functional Shift | R2: Notes | S2: GF | T2: SSS | U2: Product | V2: Project | W2: SW
A3: Generic Requirements
A4: P2RIND1 | B4: Supplier Integration | C4: P2R | D4: SX-xxxx - to be added later | E4: Process PO, PO Changes to supplier | F4: Siemens employee | G4: to send an outgoing (purchase) order or Purchase Order Change to the supplier in automated and digital manner | H4: Please refer to the prerequisites / details laid out related to the process steps "Purchase Order Release" and "Purchase Order Transfer" | I4: it is provided to the supplier with all the required data the supplier needs to process the PO or PO Changes. | J4: TBD | S4: ok | T4: ok | U4: ok | V4: ok | W4: ok
A5: P2RIND2 | B5: Supplier Integration | C5: P2R | D5: SX-xxxx - to be added later | E5: Process POR, Delivery Notes to Siemens | F5: Supplier | G5: to send Purchase Order Receipts (POR) or delivery notes in automated and digital manner | H5: Please refer to the prerequisites / details laid out related to the process steps "Purchse Order Receipt Verification" and "Goods Receipt Posting" | I5: it is provided to Siemens with all required data Siemens needs to process the POR and Goods Receipt. | J5: TBD | S5: ok | T5: ok | U5: ok | V5: ok | W5: ok
A6: Prerequisites/ Details to be considered
A7: P2RIND3 | B7: Supplier Integration | C7: P2R | D7: SX-xxxx - to be added later | E7: Purchase Order Release | H7: The Scope of the PO release process step is to prepare the final approved PO for transfer to the supplier. If there is no approval needed, the PO will be released automatically. The usage of the correct PO printout format is based on local legal requirements and internal regulations (roll-in activity). [Siemens Stationery “Corporate Design Guidelines”, Status December_2020 (S. 49)] Archiving A PDF copy of the PO printout after PO release should be stored as an attachment in S/4 for legal purposes. | S7: ok | T7: ok | U7: ok | V7: ok | W7: ok
A8: P2RIND4 | B8: Supplier Integration | C8: P2R | D8: SX-xxxx - to be added later | E8: Purchase Order Release | F8: As a purchaser, | G8: I want that the language of the PO printout corresponds to the language of supplier master data - in case country related language is not legally in used to be send out to suppliers, default language need to be considered (e.g. English) | I8: so that miscommunication towards the supplier can be avoided. | J8: TBD | S8: Needs to be addressed during localization workshops prior to SHERPA X onboarding of AREs | T8: if the language can in any case not correspond - then English | U8: ok | V8: ok | W8: Does supplier master data reflect local legal requirement? There should a check with Legal in all countries on local language requirement by law. SW currently has EN, DE and Kanji in PO printout in 3 systems. Our Legal in APAC said China mainland and Taiwan doesn't legally require Chinese translation in POs but translation helps during lawsuits and arbitration.
A9: P2RIND5 | B9: Supplier Integration | C9: P2R | D9: SX-xxxx - to be added later | E9: Purchase Order Release | F9: As a purchaser, | G9: I want to have copy of the PO printout as soon as it is created (PO or PO Change) | I9: so that a copy of for legal purposes is stored in the system. | J9: TBD | S9: ok | T9: ok | U9: ok | V9: ok | W9: ok
A10: P2RIND6 | B10: Supplier Integration | C10: P2R | D10: SX-xxxx - to be added later | E10: Purchase Order Release | F10: As a purchaser, | G10: I want to rename the PO printout from “Order” to “Order Change” in case adjustments in the PO are required | I10: so that miscommunication towards the supplier can be avoided. | J10: TBD | S10: ok | T10: ok | U10: ok | V10: ok | W10: ok
A11: P2RIND7 | B11: Supplier Integration | C11: P2R | D11: SX-xxxx - to be added later | E11: Purchase Order Release | F11: As a purchaser, | G11: I want that PO printout form is adjusted per country | I11: so that Siemens guidelines and local regulations are fulfilled. | J11: TBD | S11: Needs to be addressed during localization workshops prior to SHERPA X onboarding of AREs | T11: ok | U11: ok | V11: ok | W11: Same as row 8, what could be local regulation for our PO printout form?
A12: P2RIND8 | B12: Supplier Integration | C12: P2R | D12: SX-xxxx - to be added later | E12: Purchase Order Transfer (to the supplier) | H12: The Scope of the supplier communication process step is to ensure the correct transfer of the PO to the supplier. The supplier communication data in the PO is automatically prefilled from the supplier master data. This data can be changed manually during the PO creation process by the purchaser, e.g. replacing the prefilled email address or switching the output media from fax to email. | S12: ok | T12: ok | U12: ok | V12: ok | W12: ok
A13: P2RIND9 | B13: Supplier Integration | C13: P2R | D13: SX-xxxx - to be added later | E13: Purchase Order Transfer (to the supplier) | F13: As a purchaser, | G13: I want that PO is transferred according to the output media setting in the PO (prefilled from supplier master data, editable for purchaser) | I13: so that the PO is transferred as agreed with the supplier. | J13: TBD | S13: ok | T13: ok | U13: ok | V13: ok | W13: ok
A14: P2RIND10 | B14: Supplier Integration | C14: P2R | D14: SX-xxxx - to be added later | E14: Purchase Order Transfer (to the supplier) | F14: As a purchaser, | G14: I want to decide if a PO change should be sent to supplier | I14: so that the supplier receives only a “PO Change” document if changed data fields are relevant for them. | J14: TBD | S14: ok | T14: ok | U14: ok | V14: ok | W14: ok
A15: P2RIND11 | B15: Supplier Integration | C15: P2R | D15: SX-xxxx - to be added later | E15: Purchase Order Transfer (to the supplier) | F15: As a purchaser, | G15: I want to be able to decide if automatically initiated PO changes based on PORs (price reduction or change of delivery date) should be sent to supplier | I15: so that misunderstandings with the supplier for Siemens internal data changes can be avoided. | J15: TBD | S15: ok | T15: ok | U15: ok | V15: ok | W15: ok
A16: P2RIND12 | B16: Supplier Integration | C16: P2R | D16: SX-xxxx - to be added later | E16: Purchase Order Transfer (to the supplier) | F16: As a purchaser, | G16: I want that attachments in the PO marked as “external” should be sent to supplier (email, EDI) | I16: so that the supplier receives all relevant information. | J16: TBD | S16: ok | T16: ok | U16: ok | V16: ok | W16: ok
A17: P2RIND13 | B17: Supplier Integration | C17: P2R | D17: SX-xxxx - to be added later | E17: Purchase Order Transfer (to the supplier) | F17: As a purchaser, | G17: I want to decide (manually) if a PO should be sent to supplier (invoice already received from the supplier) | I17: so that POs for internal purposes are not sent to the supplier. | J17: TBD | S17: ok | T17: ok | U17: ok | V17: ok | W17: ok
A18: P2RIND14 | B18: Supplier Integration | C18: P2R | D18: SX-xxxx - to be added later | E18: Purchase Order Transfer (to the supplier) | F18: As a requisitioner, | G18: I want to have my contact data displayed in the PO printout and EDI | H18: as technical contact in case of inquiry of supplier | I18: so that clarifications can be processed faster. | J18: TBD | S18: ok | T18: ok | U18: ok | V18: ok | W18: ok
A19: P2RIND15 | B19: Supplier Integration | C19: P2R | D19: SX-xxxx - to be added later | E19: Purchase Order Receipt Verification | H19: The purpose of the POR process step is to ensure that the POR received from the supplier confirms the PO. A supplier has to reply to the purchase order and confirm whether the ordered quantity of goods or services can be delivered at the time and for the price requested, as well as that the Siemens terms and conditions apply. To identify possible deviations, the received POR will be matched with the corresponding PO. SHERPA workstream logistics will decide on future processing and the technical solution for this step. In general, an SAP internal realization is favored including using EDI. Input media A POR can either be received by fax, post, email or EDI. 1. PORs received by fax or post will be compared with the PO and processed manually by the purchaser. 2. PORs received via email (PDF) should be automatically read by a scanning service. The POR should be transferred automatically via EDI and follows the EDI process. 3. PORs received via email (pdf), which cannot be automatically read by a scanning service, should be sent via email to the allocated purchaser. The purchaser manually compares the POR and PO, and takes care of changes in the PO, if required. 4. PORs received via EDI, an automatic POR and PO comparison check should be conducted. EDI The following three use cases for EDI PORs applies: 1. Use case 1: Deviations beyond defined tolerances If deviations beyond the defined tolerances are identified within the system, the POR has to be send automatically to the respective purchaser with an overview of the deviations. a. Received POR The POR received via EDI. b. Compares PO and POR The system compared the POR and the corresponding PO. Deviations beyond the defined tolerances (roll-in activity) are identified. c. Assign PO The POR will be routed to the work overview of the responsible purchaser. The purchaser opens work item. d. Review deviation Purchaser manually reviews the deviations. e. Accept / reject POR Purchaser rejects or accepts deviation after clarification. f. Edit PO If deviations are accepted, the PO has to be edited and if necessary, the PO change should be resent to the supplier. 2. Use case 2: Deviations within tolerances a. Receive POR The POR received via EDI. b. System compares PO and POR The system compared the POR and the corresponding PO. Deviations within the defined tolerances (roll-in activity) are identified. c. Edit and document PO The received POR needs to be documented automatically in the PO. The PDF should be attached, and the reference number deposited under “order acknowledgement” and PO must be adjusted. d. Inform supplier about PO change (optional) Depending on criteria, the PO change needs to be sent automatically to the supplier according to the initial PO. 3. Use case 3: No deviations a. System compares PO and POR The system compared the POR and the corresponding PO. b. Document PO The received POR needs to be documented automatically in the PO. The PDF should be attached, and the reference number deposited under “order acknowledgement”. Outstanding PORs (roll-in activity) Automatic monitoring of outstanding POR line items via a scheduled system job scanning is required. based on the criteria (POR expected and GR not posted or invoice received) purchasing organization and suppliers (optional). According to pre-defined criteria, affected purchase orders should be identified and a notification should be sent to the supplier, to the purchaser and / or the requisitioner. Therefore, several levels and reminder notifications should be defined, e.g., x days after purchase order release. | S19: Post means that a booking is initiated - not in the sense of a letter | T19: ok | U19: ok | V19: ok | W19: ok
A20: P2RIND16 | B20: Supplier Integration | C20: P2R | D20: SX-xxxx - to be added later | E20: Purchase Order Receipt Verification | F20: As a purchaser, | G20: Use case 1: Deviations beyond defined tolerances - I want to receive PORs with deviations beyond tolerances in my work overview. These are automatically identified by the system by comparing EDI POR with the PO | I20: so that deviations can be clarified, and the purchaser can accept or reject the POR. | J20: TBD | S20: ok | T20: ok | U20: ok | V20: ok | W20: ok
A21: P2RIND17 | B21: Supplier Integration | C21: P2R | D21: SX-xxxx - to be added later | E21: Purchase Order Receipt Verification | F21: As a purchaser, | G21: Use case 2: Deviations within tolerances - I want to receive PORs with deviations within tolerances in my work overview. These are automatically identified by the system by comparing EDI POR with the PO | I21: so that deviations can be clarified, and the purchaser can accept or reject the POR. | J21: TBD | S21: ok | T21: ok | U21: ok | V21: ok | W21: ok
A22: P2RIND18 | B22: Supplier Integration | C22: P2R | D22: SX-xxxx - to be added later | E22: Purchase Order Receipt Verification | F22: As a purchaser, | G22: Use case 3: No deviations - I want that PORs without deviation are documented in the dedicated field in the PO | I22: so that I can see the status “POR sent”. | J22: TBD | S22: ok | T22: ok | U22: ok | V22: ok | W22: ok
A23: P2RIND19 | B23: Supplier Integration | C23: P2R | D23: SX-xxxx - to be added later | E23: Purchase Order Receipt Verification | F23: As a process owner, | G23: Tolerances for EDI PORs deviations - I want to define tolerances (lower value and higher value) for dedicated data fields (e.g. price, delivery date) | I23: so that manual effort is avoided. | J23: TBD | S23: ok | T23: ok | U23: ok | V23: ok | W23: ok
A24: P2RIND20 | B24: Supplier Integration | C24: P2R | D24: SX-xxxx - to be added later | E24: Purchase Order Receipt Verification | F24: As a purchaser, | G24: I want in the case that an existing POR which is not processed yet becomes invalid, when a new and updated POR sent from the supplier arise | I24: so that misunderstandings with the supplier can be avoided. | J24: TBD | S24: ok | T24: ok | U24: ok | V24: ok | W24: ok
A25: P2RIND21 | B25: Supplier Integration | C25: P2R | D25: SX-xxxx - to be added later | E25: Purchase Order Receipt Verification | F25: As a purchaser, | G25: I want that a POR with a partially confirmation of the PO only relies to the respective line item so that unconfirmed line items stay untouched | I25: so that errors can be avoided. | J25: TBD | S25: ok | T25: ok | U25: ok | V25: ok | W25: ok
A26: P2RIND22 | B26: Supplier Integration | C26: P2R | D26: SX-xxxx - to be added later | E26: Goods Receipt Posting | H26: In the goods receipt / performance receipt step, the business confirms the delivery of goods or services by the supplier. Variants For goods / service confirmation two variants apply: 1. Confirmation via GR posting (based on delivery). 2. Confirmation via performance receipt (based on invoice). Depended on a business decision, inclusive accounting, one or both variants can be used. A decisive reason for a specific variant is the accounting type used in PR / PO by the requisitioner. Alternatives to the existing logic are welcome. Acknowledgement via invoice webcycle Create performance process (acknowledgement based on invoice as is today). No requirements (roll-in activity) Responsibilities A GR posting should be performed by the requisitioner, a central goods recipient and incoming goods department, or every user with the respective authorization. A confirmation of performance receipt should be performed by the receiver of the assigned webcycle. Process deviations - Use case 1: GR post is not correct In general, if adjustments to the GR posting are required, a cancellation function should be supported so that a new GR post can be posted. - Use case 2: Return delivery In case of return delivery, the requisitioner or user with respective authorizations should be able to cancel the GR and post a new GR - Use case 3: GR overdue, delivery date exceeded (roll-in activity). A report function for overdue GRs should be available for the requisitioner (roll-in activity). To avoid undelivered and open POs in the system, a report functionalilty should be available for the requisitioner. Communication webcycle - Use case 1: Invoice booked; GR missing In case of an incoming invoice and missing GR, a notification (webcycle) will be sent to the requisitioner or recipient (roll-in activity). - Use case 2: Performance receipt via invoice In case of incoming invoice a notification (webcycle) will be sent to the requisitioner or recipient (roll-in activity). Archiving There is no recommendation from SCM to the businesses foreseen regarding archiving of delivery notes (roll-in activity, local legal requirements). Payment In preparation of initiating payment transactions, a three-way match needs to be conducted. After confirmation of GR or performance receipt, the document should be compared against PO and INV. A support of a 2-way match instead of 3-way match for trusted partners for a defined threshold should be considered (roll-in activity). | S26: Fine to add SW comment in requirement | T26: ok | U26: ok | V26: ok | W26: For service, 2-way match should be allowed, e.g. Requsitioner confirms service/performamce completed/receipt.
A27: P2RIND23 | B27: Supplier Integration | C27: P2R | D27: SX-xxxx - to be added later | E27: Goods Receipt Posting | F27: As a process owner, | G27: I want to get closed multiple POs via mass update (final invoice and /or final delivery flags) | I27: so that the open POs in the system can be closed (fiscal year ending). | J27: TBD | S27: ok | T27: ok | U27: ok | V27: ok | W27: ok
A28: P2RIND24 | B28: Supplier Integration | C28: P2R | D28: SX-xxxx - to be added later | E28: Goods Receipt Posting | F28: As a requisitioner, | G28: I want see my “my overdue GRs”, if the delivery date is exceeded and the GR is not posted or the PO is closed. | I28: so that delays in GR booking can be minimized. | J28: TBD | S28: ok | T28: ok | U28: ok | V28: ok | W28: ok
A29: P2RIND25 | B29: Supplier Integration | C29: P2R | D29: SX-xxxx - to be added later | E29: Goods Receipt Posting | F29: As a requisitioner, | G29: I want that the final delivery flag is set automatically if the PO amount is equal to the amount posted in the GR and invoiced amount | I29: so that POs can be closed without manual effort. | J29: TBD | S29: ok | T29: ok | U29: ok | V29: ok | W29: ok
A30: P2RIND26 | B30: Supplier Integration | C30: P2R | D30: SX-xxxx - to be added later | E30: Goods Receipt Posting | F30: As a process owner, | G30: I want to automatically notify the supplier about outstanding delivery in (already expected GR, delivery date exceeded, GR not booked (line item related)) | I30: so that manual effort is reduced. | J30: TBD | S30: ok | T30: ok | U30: ok | V30: ok | W30: ok
A31: P2RIND27 | B31: Supplier Integration | C31: P2R | D31: SX-xxxx - to be added later | E31: General - Filtering and Sorting | F31: Siemens Person | G31: ...be able to display multiple external suppliers per country/ region/ organization/ internal attributes such as supplier segmentation | I31: to provide insights across supplier base by flexibly filtering and sorting to achieve a holisitic view | S31: GF input | T31: ok | U31: ok | V31: ok | W31: ok
A32: P2RIND28 | B32: Supplier Integration | C32: P2R | D32: SX-xxxx - to be added later | E32: General - Supplier access (rights management) | F32: Siemens Buyer | G32: be able to select which information should be visible for the supplier (e.g. access rights depending on domain expert tool rights) | I32: we have flexibility to decide level of transparency | S32: ok | T32: ok | U32: ok | V32: BT Project Input (T. Reschke) Necessity of user story depending on data that should be shared | W32: ok
